[
  {
    "ID": 1,
    "Firstname": "Leon",
    "Lastname": "Müller",
    "Name": "Leon Müller",
    "Birthyear": 2018,
    "Club": "JC Sakura Berlin",
    "Association": "JV Berlin",
    "Weight": Infinity,
    "Valid": false,
    "Gender": "m",
    "Paid": true
  },
  {
    "ID": 4,
    "Firstname": "Paul",
    "Lastname": "Schneider",
    "Name": "Paul Schneider",
    "Birthyear": 2017,
    "Club": "JC Sakura Berlin",
    "Association": "JV Berlin",
    "Weight": 815.0,
    "Valid": false,
    "Gender": "male",
    "Paid": true
  },
  {
    "ID": 5,
    "Firstname": "Tim",
    "Lastname": "Weber",
    "Name": "Tim Weber",
    "Birthyear": 2015,
    "Club": "TSV Bushido Köln",
    "Association": "NWJV",
    "Weight": 0.0,
    "Valid": false,
    "Gender": "male",
    "Paid": true
  },
  {
    "ID": 8,
    "Firstname": "Jonas",
    "Lastname": "Fischer",
    "Name": "Jonas Fischer",
    "Birthyear": 2014,
    "Club": "TSV Bushido Köln",
    "Association": "NWJV",
    "Weight": 0.0,
    "Valid": false,
    "Gender": "male",
    "Paid": true
  },
  {
    "ID": 9,
    "Firstname": "Elias",
    "Lastname": "Wagner",
    "Name": "Elias Wagner",
    "Birthyear": 2013,
    "Club": "JC Leipzig",
    "Association": "JV Sachsen",
    "Weight": 0.0,
    "Valid": false,
    "Gender": "male",
    "Paid": true
  },
  {
    "ID": 10,
    "Firstname": "Luca",
    "Lastname": "Hofmann",
    "Name": "Luca Hofmann",
    "Birthyear": 2012,
    "Club": "JC Leipzig",
    "Association": "JV Sachsen",
    "Weight": 0.0,
    "Valid": false,
    "Gender": "male",
    "Paid": false
  },
  {
    "ID": 15,
    "Firstname": "Noah",
    "Lastname": "Becker",
    "Name": "Noah Becker",
    "Birthyear": 2011,
    "Club": "Budoclub München",
    "Association": "BJV",
    "Weight": 0.0,
    "Valid": false,
    "Gender": "male",
    "Paid": false
  },
  {
    "ID": 16,
    "Firstname": "David",
    "Lastname": "Richter",
    "Name": "David Richter",
    "Birthyear": 2009,
    "Club": "Budoclub München",
    "Association": "BJV",
    "Weight": 0.0,
    "Valid": false,
    "Gender": "male",
    "Paid": false
  },
  {
    "ID": 17,
    "Firstname": "Marco",
    "Lastname": "Schulz",
    "Name": "Marco Schulz",
    "Birthyear": 2006,
    "Club": "JC Hamburg Nord",
    "Association": "HJV",
    "Weight": 0.0,
    "Valid": false,
    "Gender": "male",
    "Paid": true
  },
  {
    "ID": 18,
    "Firstname": "Tobias",
    "Lastname": "König",
    "Name": "Tobias König",
    "Birthyear": 2003,
    "Club": "JC Hamburg Nord",
    "Association": "HJV",
    "Weight": 0.0,
    "Valid": false,
    "Gender": "male",
    "Paid": true
  },
  {
    "ID": 21,
    "Firstname": "Felix",
    "Lastname": "Zimmermann",
    "Name": "Felix Zimmermann",
    "Birthyear": 2017,
    "Club": "Eintracht Frankfurt Judo",
    "Association": "HJV",
    "Weight": 0.0,
    "Valid": false,
    "Gender": "male",
    "Paid": false
  },
  {
    "ID": 23,
    "Firstname": "Ben",
    "Lastname": "Schäfer",
    "Name": "Ben Schäfer",
    "Birthyear": 2014,
    "Club": "JC Köln Süd",
    "Association": "NWJV",
    "Weight": 0.0,
    "Valid": false,
    "Gender": "male",
    "Paid": true
  },
  {
    "ID": 25,
    "Firstname": "Jonas",
    "Lastname": "Peters",
    "Name": "Jonas Peters",
    "Birthyear": 2012,
    "Club": "SV Blau-Weiß Berlin",
    "Association": "JV Berlin",
    "Weight": 0.0,
    "Valid": false,
    "Gender": "male",
    "Paid": false
  },
  {
    "ID": 27,
    "Firstname": "Tom",
    "Lastname": "Kranz",
    "Name": "Tom Kranz",
    "Birthyear": 2009,
    "Club": "JC Hannover",
    "Association": "NJV",
    "Weight": 0.0,
    "Valid": false,
    "Gender": "male",
    "Paid": false
  },
  {
    "ID": 29,
    "Firstname": "Lukas",
    "Lastname": "Brandt",
    "Name": "Lukas Brandt",
    "Birthyear": 2005,
    "Club": "TSV München Ost",
    "Association": "BJV",
    "Weight": 0.0,
    "Valid": false,
    "Gender": "male",
    "Paid": false
  },
  {
    "ID": 31,
    "Firstname": "Max",
    "Lastname": "Scholz",
    "Name": "Max Scholz",
    "Birthyear": 1998,
    "Club": "Judo Club Dresden",
    "Association": "JV Sachsen",
    "Weight": 0.0,
    "Valid": false,
    "Gender": "male",
    "Paid": true
  },
  {
    "ID": 33,
    "Firstname": "Finn",
    "Lastname": "Arnold",
    "Name": "Finn Arnold",
    "Birthyear": 2016,
    "Club": "SC Leipzig Judo",
    "Association": "JV Sachsen",
    "Weight": 0.0,
    "Valid": false,
    "Gender": "male",
    "Paid": true
  },
  {
    "ID": 35,
    "Firstname": "Oskar",
    "Lastname": "Dietrich",
    "Name": "Oskar Dietrich",
    "Birthyear": 2014,
    "Club": "JC Potsdam",
    "Association": "JV Berlin",
    "Weight": 0.0,
    "Valid": false,
    "Gender": "male",
    "Paid": false
  },
  {
    "ID": 37,
    "Firstname": "Niklas",
    "Lastname": "Graf",
    "Name": "Niklas Graf",
    "Birthyear": 2013,
    "Club": "TSV Stuttgart Nord",
    "Association": "WJV",
    "Weight": 0.0,
    "Valid": false,
    "Gender": "male",
    "Paid": true
  },
  {
    "ID": 39,
    "Firstname": "Moritz",
    "Lastname": "Jung",
    "Name": "Moritz Jung",
    "Birthyear": 2011,
    "Club": "SV Hamburg Süd",
    "Association": "HJV",
    "Weight": 0.0,
    "Valid": false,
    "Gender": "male",
    "Paid": true
  },
  {
    "ID": 41,
    "Firstname": "Paul",
    "Lastname": "Lang",
    "Name": "Paul Lang",
    "Birthyear": 2009,
    "Club": "JC Nürnberg",
    "Association": "BJV",
    "Weight": 0.0,
    "Valid": false,
    "Gender": "male",
    "Paid": false
  },
  {
    "ID": 43,
    "Firstname": "Jan",
    "Lastname": "Neubert",
    "Name": "Jan Neubert",
    "Birthyear": 2005,
    "Club": "TV Düsseldorf",
    "Association": "NWJV",
    "Weight": 0.0,
    "Valid": false,
    "Gender": "male",
    "Paid": true
  },
  {
    "ID": 45,
    "Firstname": "Eric",
    "Lastname": "Pohl",
    "Name": "Eric Pohl",
    "Birthyear": 1998,
    "Club": "Judo Team Hannover",
    "Association": "NJV",
    "Weight": 0.0,
    "Valid": false,
    "Gender": "male",
    "Paid": true
  },
  {
    "ID": 47,
    "Firstname": "Daniel",
    "Lastname": "Schwarz",
    "Name": "Daniel Schwarz",
    "Birthyear": 1995,
    "Club": "SV Karlsruhe",
    "Association": "BJV",
    "Weight": 0.0,
    "Valid": false,
    "Gender": "male",
    "Paid": true
  },
  {
    "ID": 49,
    "Firstname": "Mats",
    "Lastname": "Ulrich",
    "Name": "Mats Ulrich",
    "Birthyear": 2013,
    "Club": "JC Rostock",
    "Association": "MVJV",
    "Weight": 0.0,
    "Valid": false,
    "Gender": "male",
    "Paid": true
  },
  {
    "ID": 51,
    "Firstname": "Tim",
    "Lastname": "Schneider",
    "Name": "Tim Schneider",
    "Birthyear": 2017,
    "Club": "JC Leipzig",
    "Association": "JV Sachsen",
    "Weight": 0.0,
    "Valid": false,
    "Gender": "male",
    "Paid": false
  },
  {
    "ID": 52,
    "Firstname": "Moritz",
    "Lastname": "Schäfer",
    "Name": "Moritz Schäfer",
    "Birthyear": 2016,
    "Club": "PSV Frankfurt",
    "Association": "HJV",
    "Weight": 0.0,
    "Valid": false,
    "Gender": "male",
    "Paid": false
  },
  {
    "ID": 55,
    "Firstname": "Paul",
    "Lastname": "Wagner",
    "Name": "Paul Wagner",
    "Birthyear": 1997,
    "Club": "JC Hannover",
    "Association": "NJV",
    "Weight": 0.0,
    "Valid": false,
    "Gender": "male",
    "Paid": false
  },
  {
    "ID": 56,
    "Firstname": "Lukas",
    "Lastname": "Fischer",
    "Name": "Lukas Fischer",
    "Birthyear": 2019,
    "Club": "SV Potsdam",
    "Association": "JV Berlin",
    "Weight": 0.0,
    "Valid": false,
    "Gender": "male",
    "Paid": true
  },
  {
    "ID": 57,
    "Firstname": "Tom",
    "Lastname": "Hoffmann",
    "Name": "Tom Hoffmann",
    "Birthyear": 2011,
    "Club": "JC Berlin Süd",
    "Association": "JV Berlin",
    "Weight": 0.0,
    "Valid": false,
    "Gender": "male",
    "Paid": false
  },
  {
    "ID": 59,
    "Firstname": "Elias",
    "Lastname": "Wagner",
    "Name": "Elias Wagner",
    "Birthyear": 2016,
    "Club": "PSV Frankfurt",
    "Association": "HJV",
    "Weight": 0.0,
    "Valid": false,
    "Gender": "male",
    "Paid": true
  },
  {
    "ID": 62,
    "Firstname": "Jonas",
    "Lastname": "Schneider",
    "Name": "Jonas Schneider",
    "Birthyear": 2018,
    "Club": "Budosport Stuttgart",
    "Association": "WJV",
    "Weight": 0.0,
    "Valid": false,
    "Gender": "male",
    "Paid": true
  },
  {
    "ID": 66,
    "Firstname": "Paul",
    "Lastname": "Schäfer",
    "Name": "Paul Schäfer",
    "Birthyear": 2007,
    "Club": "JC Hamburg Nord",
    "Association": "HJV",
    "Weight": 0.0,
    "Valid": false,
    "Gender": "male",
    "Paid": false
  },
  {
    "ID": 67,
    "Firstname": "Leon",
    "Lastname": "Fischer",
    "Name": "Leon Fischer",
    "Birthyear": 1999,
    "Club": "PSV Frankfurt",
    "Association": "HJV",
    "Weight": 0.0,
    "Valid": false,
    "Gender": "male",
    "Paid": false
  },
  {
    "ID": 68,
    "Firstname": "Tim",
    "Lastname": "Fischer",
    "Name": "Tim Fischer",
    "Birthyear": 2019,
    "Club": "MTV Karlsruhe",
    "Association": "BJV",
    "Weight": 0.0,
    "Valid": false,
    "Gender": "male",
    "Paid": true
  },
  {
    "ID": 69,
    "Firstname": "Lukas",
    "Lastname": "Hoffmann",
    "Name": "Lukas Hoffmann",
    "Birthyear": 2008,
    "Club": "JC Hannover",
    "Association": "NJV",
    "Weight": 0.0,
    "Valid": false,
    "Gender": "male",
    "Paid": true
  },
  {
    "ID": 70,
    "Firstname": "Tom",
    "Lastname": "Weber",
    "Name": "Tom Weber",
    "Birthyear": 2015,
    "Club": "JC Hamburg Nord",
    "Association": "HJV",
    "Weight": 0.0,
    "Valid": false,
    "Gender": "male",
    "Paid": false
  },
  {
    "ID": 71,
    "Firstname": "Paul",
    "Lastname": "Schmidt",
    "Name": "Paul Schmidt",
    "Birthyear": 2018,
    "Club": "Budosport Stuttgart",
    "Association": "WJV",
    "Weight": 0.0,
    "Valid": false,
    "Gender": "male",
    "Paid": true
  },
  {
    "ID": 73,
    "Firstname": "Max",
    "Lastname": "Hoffmann",
    "Name": "Max Hoffmann",
    "Birthyear": 2017,
    "Club": "JC München",
    "Association": "BJV",
    "Weight": 0.0,
    "Valid": false,
    "Gender": "male",
    "Paid": false
  },
  {
    "ID": 74,
    "Firstname": "Paul",
    "Lastname": "Weber",
    "Name": "Paul Weber",
    "Birthyear": 2013,
    "Club": "TSV Köln",
    "Association": "NWJV",
    "Weight": 0.0,
    "Valid": false,
    "Gender": "male",
    "Paid": true
  },
  {
    "ID": 77,
    "Firstname": "Lukas",
    "Lastname": "Schmidt",
    "Name": "Lukas Schmidt",
    "Birthyear": 2011,
    "Club": "JC Leipzig",
    "Association": "JV Sachsen",
    "Weight": 0.0,
    "Valid": false,
    "Gender": "male",
    "Paid": false
  },
  {
    "ID": 78,
    "Firstname": "Max",
    "Lastname": "Schäfer",
    "Name": "Max Schäfer",
    "Birthyear": 2014,
    "Club": "JC Leipzig",
    "Association": "JV Sachsen",
    "Weight": 0.0,
    "Valid": false,
    "Gender": "male",
    "Paid": false
  },
  {
    "ID": 79,
    "Firstname": "Elias",
    "Lastname": "Wagner",
    "Name": "Elias Wagner",
    "Birthyear": 2011,
    "Club": "JC Hannover",
    "Association": "NJV",
    "Weight": 0.0,
    "Valid": false,
    "Gender": "male",
    "Paid": false
  },
  {
    "ID": 80,
    "Firstname": "Tim",
    "Lastname": "Müller",
    "Name": "Tim Müller",
    "Birthyear": 2015,
    "Club": "Budosport Stuttgart",
    "Association": "WJV",
    "Weight": 0.0,
    "Valid": false,
    "Gender": "male",
    "Paid": true
  },
  {
    "ID": 81,
    "Firstname": "Paul",
    "Lastname": "Hoffmann",
    "Name": "Paul Hoffmann",
    "Birthyear": 2009,
    "Club": "JC Hamburg Nord",
    "Association": "HJV",
    "Weight": 0.0,
    "Valid": false,
    "Gender": "male",
    "Paid": true
  },
  {
    "ID": 82,
    "Firstname": "Max",
    "Lastname": "Schäfer",
    "Name": "Max Schäfer",
    "Birthyear": 2012,
    "Club": "JC Hannover",
    "Association": "NJV",
    "Weight": 0.0,
    "Valid": false,
    "Gender": "male",
    "Paid": true
  },
  {
    "ID": 84,
    "Firstname": "Paul",
    "Lastname": "Müller",
    "Name": "Paul Müller",
    "Birthyear": 2019,
    "Club": "JC Hamburg Nord",
    "Association": "HJV",
    "Weight": 0.0,
    "Valid": false,
    "Gender": "male",
    "Paid": false
  },
  {
    "ID": 85,
    "Firstname": "Finn",
    "Lastname": "Wagner",
    "Name": "Finn Wagner",
    "Birthyear": 2012,
    "Club": "Budosport Stuttgart",
    "Association": "WJV",
    "Weight": 0.0,
    "Valid": false,
    "Gender": "male",
    "Paid": false
  },
  {
    "ID": 86,
    "Firstname": "Noah",
    "Lastname": "Bauer",
    "Name": "Noah Bauer",
    "Birthyear": 2017,
    "Club": "JC Hannover",
    "Association": "NJV",
    "Weight": 0.0,
    "Valid": false,
    "Gender": "male",
    "Paid": true
  },
  {
    "ID": 94,
    "Firstname": "Ben",
    "Lastname": "Bauer",
    "Name": "Ben Bauer",
    "Birthyear": 2012,
    "Club": "Budosport Stuttgart",
    "Association": "WJV",
    "Weight": 0.0,
    "Valid": false,
    "Gender": "male",
    "Paid": true
  },
  {
    "ID": 95,
    "Firstname": "Noah",
    "Lastname": "Bauer",
    "Name": "Noah Bauer",
    "Birthyear": 2005,
    "Club": "JC Berlin Süd",
    "Association": "JV Berlin",
    "Weight": 0.0,
    "Valid": false,
    "Gender": "male",
    "Paid": true
  },
  {
    "ID": 96,
    "Firstname": "Noah",
    "Lastname": "Schäfer",
    "Name": "Noah Schäfer",
    "Birthyear": 2015,
    "Club": "PSV Frankfurt",
    "Association": "HJV",
    "Weight": 0.0,
    "Valid": false,
    "Gender": "male",
    "Paid": false
  },
  {
    "ID": 97,
    "Firstname": "Lukas",
    "Lastname": "Fischer",
    "Name": "Lukas Fischer",
    "Birthyear": 2019,
    "Club": "JC München",
    "Association": "BJV",
    "Weight": 0.0,
    "Valid": false,
    "Gender": "male",
    "Paid": true
  },
  {
    "ID": 99,
    "Firstname": "Ben",
    "Lastname": "Müller",
    "Name": "Ben Müller",
    "Birthyear": 2016,
    "Club": "Budosport Stuttgart",
    "Association": "WJV",
    "Weight": 0.0,
    "Valid": false,
    "Gender": "male",
    "Paid": true
  },
  {
    "ID": 101,
    "Firstname": "Jonas",
    "Lastname": "Bauer",
    "Name": "Jonas Bauer",
    "Birthyear": 2012,
    "Club": "JC Berlin Süd",
    "Association": "JV Berlin",
    "Weight": 0.0,
    "Valid": false,
    "Gender": "male",
    "Paid": false
  },
  {
    "ID": 102,
    "Firstname": "Elias",
    "Lastname": "Koch",
    "Name": "Elias Koch",
    "Birthyear": 2006,
    "Club": "JC Hannover",
    "Association": "NJV",
    "Weight": 0.0,
    "Valid": false,
    "Gender": "male",
    "Paid": true
  },
  {
    "ID": 104,
    "Firstname": "Paul",
    "Lastname": "Schäfer",
    "Name": "Paul Schäfer",
    "Birthyear": 2012,
    "Club": "JC Leipzig",
    "Association": "JV Sachsen",
    "Weight": 0.0,
    "Valid": false,
    "Gender": "male",
    "Paid": true
  },
  {
    "ID": 105,
    "Firstname": "Finn",
    "Lastname": "Bauer",
    "Name": "Finn Bauer",
    "Birthyear": 1999,
    "Club": "JC Berlin Süd",
    "Association": "JV Berlin",
    "Weight": 0.0,
    "Valid": false,
    "Gender": "male",
    "Paid": false
  },
  {
    "ID": 107,
    "Firstname": "Jonas",
    "Lastname": "Müller",
    "Name": "Jonas Müller",
    "Birthyear": 2016,
    "Club": "SV Potsdam",
    "Association": "JV Berlin",
    "Weight": 0.0,
    "Valid": false,
    "Gender": "male",
    "Paid": true
  },
  {
    "ID": 110,
    "Firstname": "Tim",
    "Lastname": "Fischer",
    "Name": "Tim Fischer",
    "Birthyear": 2017,
    "Club": "PSV Frankfurt",
    "Association": "HJV",
    "Weight": 0.0,
    "Valid": false,
    "Gender": "male",
    "Paid": false
  },
  {
    "ID": 114,
    "Firstname": "Jonas",
    "Lastname": "Schmidt",
    "Name": "Jonas Schmidt",
    "Birthyear": 2015,
    "Club": "PSV Frankfurt",
    "Association": "HJV",
    "Weight": 0.0,
    "Valid": false,
    "Gender": "male",
    "Paid": true
  },
  {
    "ID": 116,
    "Firstname": "Tim",
    "Lastname": "Weber",
    "Name": "Tim Weber",
    "Birthyear": 1999,
    "Club": "SV Potsdam",
    "Association": "JV Berlin",
    "Weight": 0.0,
    "Valid": false,
    "Gender": "male",
    "Paid": true
  },
  {
    "ID": 117,
    "Firstname": "Jonas",
    "Lastname": "Bauer",
    "Name": "Jonas Bauer",
    "Birthyear": 1996,
    "Club": "TSV Köln",
    "Association": "NWJV",
    "Weight": 0.0,
    "Valid": false,
    "Gender": "male",
    "Paid": false
  },
  {
    "ID": 119,
    "Firstname": "Tim",
    "Lastname": "Meyer",
    "Name": "Tim Meyer",
    "Birthyear": 2007,
    "Club": "MTV Karlsruhe",
    "Association": "BJV",
    "Weight": 0.0,
    "Valid": false,
    "Gender": "male",
    "Paid": false
  },
  {
    "ID": 120,
    "Firstname": "Jonas",
    "Lastname": "Weber",
    "Name": "Jonas Weber",
    "Birthyear": 2014,
    "Club": "JC Hamburg Nord",
    "Association": "HJV",
    "Weight": 0.0,
    "Valid": false,
    "Gender": "male",
    "Paid": true
  },
  {
    "ID": 122,
    "Firstname": "Moritz",
    "Lastname": "Becker",
    "Name": "Moritz Becker",
    "Birthyear": 2012,
    "Club": "SV Potsdam",
    "Association": "JV Berlin",
    "Weight": 0.0,
    "Valid": false,
    "Gender": "male",
    "Paid": false
  },
  {
    "ID": 123,
    "Firstname": "Max",
    "Lastname": "Wagner",
    "Name": "Max Wagner",
    "Birthyear": 2008,
    "Club": "Budosport Stuttgart",
    "Association": "WJV",
    "Weight": 0.0,
    "Valid": false,
    "Gender": "male",
    "Paid": false
  },
  {
    "ID": 127,
    "Firstname": "Finn",
    "Lastname": "Schmidt",
    "Name": "Finn Schmidt",
    "Birthyear": 2002,
    "Club": "PSV Frankfurt",
    "Association": "HJV",
    "Weight": 0.0,
    "Valid": false,
    "Gender": "male",
    "Paid": false
  },
  {
    "ID": 131,
    "Firstname": "Ben",
    "Lastname": "Koch",
    "Name": "Ben Koch",
    "Birthyear": 1998,
    "Club": "Budosport Stuttgart",
    "Association": "WJV",
    "Weight": 0.0,
    "Valid": false,
    "Gender": "male",
    "Paid": true
  },
  {
    "ID": 132,
    "Firstname": "Elias",
    "Lastname": "Fischer",
    "Name": "Elias Fischer",
    "Birthyear": 2014,
    "Club": "MTV Karlsruhe",
    "Association": "BJV",
    "Weight": 0.0,
    "Valid": false,
    "Gender": "male",
    "Paid": false
  },
  {
    "ID": 134,
    "Firstname": "Finn",
    "Lastname": "Weber",
    "Name": "Finn Weber",
    "Birthyear": 2009,
    "Club": "JC Hannover",
    "Association": "NJV",
    "Weight": 0.0,
    "Valid": false,
    "Gender": "male",
    "Paid": false
  },
  {
    "ID": 136,
    "Firstname": "Tim",
    "Lastname": "Becker",
    "Name": "Tim Becker",
    "Birthyear": 2010,
    "Club": "PSV Frankfurt",
    "Association": "HJV",
    "Weight": 0.0,
    "Valid": false,
    "Gender": "male",
    "Paid": false
  },
  {
    "ID": 137,
    "Firstname": "Max",
    "Lastname": "Schneider",
    "Name": "Max Schneider",
    "Birthyear": 2015,
    "Club": "PSV Frankfurt",
    "Association": "HJV",
    "Weight": 0.0,
    "Valid": false,
    "Gender": "male",
    "Paid": false
  },
  {
    "ID": 143,
    "Firstname": "Finn",
    "Lastname": "Fischer",
    "Name": "Finn Fischer",
    "Birthyear": 2013,
    "Club": "JC Hannover",
    "Association": "NJV",
    "Weight": 0.0,
    "Valid": false,
    "Gender": "male",
    "Paid": true
  },
  {
    "ID": 144,
    "Firstname": "Elias",
    "Lastname": "Schneider",
    "Name": "Elias Schneider",
    "Birthyear": 2010,
    "Club": "TSV Köln",
    "Association": "NWJV",
    "Weight": 0.0,
    "Valid": false,
    "Gender": "male",
    "Paid": false
  },
  {
    "ID": 150,
    "Firstname": "Jonas",
    "Lastname": "Schneider",
    "Name": "Jonas Schneider",
    "Birthyear": 2016,
    "Club": "SV Potsdam",
    "Association": "JV Berlin",
    "Weight": 0.0,
    "Valid": false,
    "Gender": "male",
    "Paid": true
  },
  {
    "ID": 152,
    "Firstname": "Paul",
    "Lastname": "Becker",
    "Name": "Paul Becker",
    "Birthyear": 2019,
    "Club": "JC Berlin Süd",
    "Association": "JV Berlin",
    "Weight": 0.0,
    "Valid": false,
    "Gender": "male",
    "Paid": true
  },
  {
    "ID": 153,
    "Firstname": "Finn",
    "Lastname": "Hoffmann",
    "Name": "Finn Hoffmann",
    "Birthyear": 2016,
    "Club": "JC München",
    "Association": "BJV",
    "Weight": 0.0,
    "Valid": false,
    "Gender": "male",
    "Paid": true
  },
  {
    "ID": 154,
    "Firstname": "Moritz",
    "Lastname": "Schmidt",
    "Name": "Moritz Schmidt",
    "Birthyear": 2009,
    "Club": "PSV Frankfurt",
    "Association": "HJV",
    "Weight": 0.0,
    "Valid": false,
    "Gender": "male",
    "Paid": true
  },
  {
    "ID": 155,
    "Firstname": "Ben",
    "Lastname": "Bauer",
    "Name": "Ben Bauer",
    "Birthyear": 2012,
    "Club": "TSV Köln",
    "Association": "NWJV",
    "Weight": 0.0,
    "Valid": false,
    "Gender": "male",
    "Paid": true
  },
  {
    "ID": 158,
    "Firstname": "Finn",
    "Lastname": "Weber",
    "Name": "Finn Weber",
    "Birthyear": 2010,
    "Club": "JC Hannover",
    "Association": "NJV",
    "Weight": 0.0,
    "Valid": false,
    "Gender": "male",
    "Paid": false
  },
  {
    "ID": 159,
    "Firstname": "Paul",
    "Lastname": "Müller",
    "Name": "Paul Müller",
    "Birthyear": 2019,
    "Club": "Budosport Stuttgart",
    "Association": "WJV",
    "Weight": 0.0,
    "Valid": false,
    "Gender": "male",
    "Paid": false
  },
  {
    "ID": 160,
    "Firstname": "Ben",
    "Lastname": "Becker",
    "Name": "Ben Becker",
    "Birthyear": 2001,
    "Club": "JC Leipzig",
    "Association": "JV Sachsen",
    "Weight": 0.0,
    "Valid": false,
    "Gender": "male",
    "Paid": true
  },
  {
    "ID": 161,
    "Firstname": "Lukas",
    "Lastname": "Bauer",
    "Name": "Lukas Bauer",
    "Birthyear": 2013,
    "Club": "JC Hamburg Nord",
    "Association": "HJV",
    "Weight": 0.0,
    "Valid": false,
    "Gender": "male",
    "Paid": false
  },
  {
    "ID": 163,
    "Firstname": "Moritz",
    "Lastname": "Becker",
    "Name": "Moritz Becker",
    "Birthyear": 2015,
    "Club": "JC Leipzig",
    "Association": "JV Sachsen",
    "Weight": 0.0,
    "Valid": false,
    "Gender": "male",
    "Paid": true
  },
  {
    "ID": 164,
    "Firstname": "Ben",
    "Lastname": "Schäfer",
    "Name": "Ben Schäfer",
    "Birthyear": 2014,
    "Club": "Budosport Stuttgart",
    "Association": "WJV",
    "Weight": 0.0,
    "Valid": false,
    "Gender": "male",
    "Paid": true
  },
  {
    "ID": 166,
    "Firstname": "Finn",
    "Lastname": "Schmidt",
    "Name": "Finn Schmidt",
    "Birthyear": 2011,
    "Club": "SV Potsdam",
    "Association": "JV Berlin",
    "Weight": 0.0,
    "Valid": false,
    "Gender": "male",
    "Paid": false
  },
  {
    "ID": 167,
    "Firstname": "Moritz",
    "Lastname": "Meyer",
    "Name": "Moritz Meyer",
    "Birthyear": 2011,
    "Club": "Budosport Stuttgart",
    "Association": "WJV",
    "Weight": 0.0,
    "Valid": false,
    "Gender": "male",
    "Paid": true
  },
  {
    "ID": 172,
    "Firstname": "Jonas",
    "Lastname": "Hoffmann",
    "Name": "Jonas Hoffmann",
    "Birthyear": 2011,
    "Club": "JC München",
    "Association": "BJV",
    "Weight": 0.0,
    "Valid": false,
    "Gender": "male",
    "Paid": false
  },
  {
    "ID": 173,
    "Firstname": "Tom",
    "Lastname": "Bauer",
    "Name": "Tom Bauer",
    "Birthyear": 2015,
    "Club": "JC München",
    "Association": "BJV",
    "Weight": 0.0,
    "Valid": false,
    "Gender": "male",
    "Paid": true
  },
  {
    "ID": 175,
    "Firstname": "Ben",
    "Lastname": "Hoffmann",
    "Name": "Ben Hoffmann",
    "Birthyear": 2017,
    "Club": "JC Berlin Süd",
    "Association": "JV Berlin",
    "Weight": 0.0,
    "Valid": false,
    "Gender": "male",
    "Paid": true
  },
  {
    "ID": 176,
    "Firstname": "Lukas",
    "Lastname": "Müller",
    "Name": "Lukas Müller",
    "Birthyear": 1996,
    "Club": "JC München",
    "Association": "BJV",
    "Weight": 0.0,
    "Valid": false,
    "Gender": "male",
    "Paid": false
  },
  {
    "ID": 177,
    "Firstname": "Tom",
    "Lastname": "Schmidt",
    "Name": "Tom Schmidt",
    "Birthyear": 2012,
    "Club": "JC Hamburg Nord",
    "Association": "HJV",
    "Weight": 0.0,
    "Valid": false,
    "Gender": "male",
    "Paid": false
  },
  {
    "ID": 182,
    "Firstname": "Leon",
    "Lastname": "Koch",
    "Name": "Leon Koch",
    "Birthyear": 2016,
    "Club": "JC Hannover",
    "Association": "NJV",
    "Weight": 0.0,
    "Valid": false,
    "Gender": "male",
    "Paid": true
  },
  {
    "ID": 184,
    "Firstname": "Finn",
    "Lastname": "Müller",
    "Name": "Finn Müller",
    "Birthyear": 2005,
    "Club": "SV Potsdam",
    "Association": "JV Berlin",
    "Weight": 0.0,
    "Valid": false,
    "Gender": "male",
    "Paid": true
  },
  {
    "ID": 185,
    "Firstname": "Noah",
    "Lastname": "Müller",
    "Name": "Noah Müller",
    "Birthyear": 2017,
    "Club": "JC Hamburg Nord",
    "Association": "HJV",
    "Weight": 0.0,
    "Valid": false,
    "Gender": "male",
    "Paid": false
  },
  {
    "ID": 187,
    "Firstname": "Tim",
    "Lastname": "Schäfer",
    "Name": "Tim Schäfer",
    "Birthyear": 2011,
    "Club": "JC Hamburg Nord",
    "Association": "HJV",
    "Weight": 0.0,
    "Valid": false,
    "Gender": "male",
    "Paid": true
  },
  {
    "ID": 190,
    "Firstname": "Leon",
    "Lastname": "Koch",
    "Name": "Leon Koch",
    "Birthyear": 2001,
    "Club": "SV Potsdam",
    "Association": "JV Berlin",
    "Weight": 0.0,
    "Valid": false,
    "Gender": "male",
    "Paid": false
  },
  {
    "ID": 193,
    "Firstname": "Moritz",
    "Lastname": "Schneider",
    "Name": "Moritz Schneider",
    "Birthyear": 2018,
    "Club": "JC München",
    "Association": "BJV",
    "Weight": 0.0,
    "Valid": false,
    "Gender": "male",
    "Paid": false
  },
  {
    "ID": 194,
    "Firstname": "Lukas",
    "Lastname": "Weber",
    "Name": "Lukas Weber",
    "Birthyear": 2014,
    "Club": "JC Hannover",
    "Association": "NJV",
    "Weight": 0.0,
    "Valid": false,
    "Gender": "male",
    "Paid": true
  },
  {
    "ID": 195,
    "Firstname": "Tim",
    "Lastname": "Koch",
    "Name": "Tim Koch",
    "Birthyear": 1995,
    "Club": "SV Potsdam",
    "Association": "JV Berlin",
    "Weight": 0.0,
    "Valid": false,
    "Gender": "male",
    "Paid": false
  },
  {
    "ID": 198,
    "Firstname": "Noah",
    "Lastname": "Schneider",
    "Name": "Noah Schneider",
    "Birthyear": 2012,
    "Club": "JC München",
    "Association": "BJV",
    "Weight": 0.0,
    "Valid": false,
    "Gender": "male",
    "Paid": true
  },
  {
    "ID": 201,
    "Firstname": "Lukas",
    "Lastname": "Fischer",
    "Name": "Lukas Fischer",
    "Birthyear": 2015,
    "Club": "PSV Frankfurt",
    "Association": "HJV",
    "Weight": 0.0,
    "Valid": false,
    "Gender": "male",
    "Paid": false
  },
  {
    "ID": 202,
    "Firstname": "Paul",
    "Lastname": "Wagner",
    "Name": "Paul Wagner",
    "Birthyear": 2014,
    "Club": "JC Berlin Süd",
    "Association": "JV Berlin",
    "Weight": 0.0,
    "Valid": false,
    "Gender": "male",
    "Paid": true
  },
  {
    "ID": 203,
    "Firstname": "Paul",
    "Lastname": "Schneider",
    "Name": "Paul Schneider",
    "Birthyear": 2015,
    "Club": "JC Hamburg Nord",
    "Association": "HJV",
    "Weight": 0.0,
    "Valid": false,
    "Gender": "male",
    "Paid": true
  },
  {
    "ID": 209,
    "Firstname": "Elias",
    "Lastname": "Schneider",
    "Name": "Elias Schneider",
    "Birthyear": 2018,
    "Club": "Budosport Stuttgart",
    "Association": "WJV",
    "Weight": 0.0,
    "Valid": false,
    "Gender": "male",
    "Paid": false
  },
  {
    "ID": 210,
    "Firstname": "Jonas",
    "Lastname": "Meyer",
    "Name": "Jonas Meyer",
    "Birthyear": 2014,
    "Club": "MTV Karlsruhe",
    "Association": "BJV",
    "Weight": 0.0,
    "Valid": false,
    "Gender": "male",
    "Paid": false
  },
  {
    "ID": 212,
    "Firstname": "Leon",
    "Lastname": "Meyer",
    "Name": "Leon Meyer",
    "Birthyear": 2012,
    "Club": "SV Potsdam",
    "Association": "JV Berlin",
    "Weight": 0.0,
    "Valid": false,
    "Gender": "male",
    "Paid": true
  },
  {
    "ID": 217,
    "Firstname": "Lukas",
    "Lastname": "Bauer",
    "Name": "Lukas Bauer",
    "Birthyear": 2005,
    "Club": "Budosport Stuttgart",
    "Association": "WJV",
    "Weight": 0.0,
    "Valid": false,
    "Gender": "male",
    "Paid": true
  },
  {
    "ID": 218,
    "Firstname": "Leon",
    "Lastname": "Müller",
    "Name": "Leon Müller",
    "Birthyear": 2011,
    "Club": "PSV Frankfurt",
    "Association": "HJV",
    "Weight": 0.0,
    "Valid": false,
    "Gender": "male",
    "Paid": true
  },
  {
    "ID": 219,
    "Firstname": "Noah",
    "Lastname": "Schneider",
    "Name": "Noah Schneider",
    "Birthyear": 2014,
    "Club": "PSV Frankfurt",
    "Association": "HJV",
    "Weight": 0.0,
    "Valid": false,
    "Gender": "male",
    "Paid": false
  },
  {
    "ID": 226,
    "Firstname": "Tom",
    "Lastname": "Bauer",
    "Name": "Tom Bauer",
    "Birthyear": 2011,
    "Club": "SV Potsdam",
    "Association": "JV Berlin",
    "Weight": 0.0,
    "Valid": false,
    "Gender": "male",
    "Paid": true
  },
  {
    "ID": 227,
    "Firstname": "Tom",
    "Lastname": "Schneider",
    "Name": "Tom Schneider",
    "Birthyear": 2017,
    "Club": "JC München",
    "Association": "BJV",
    "Weight": 0.0,
    "Valid": false,
    "Gender": "male",
    "Paid": false
  },
  {
    "ID": 229,
    "Firstname": "Paul",
    "Lastname": "Becker",
    "Name": "Paul Becker",
    "Birthyear": 2015,
    "Club": "PSV Frankfurt",
    "Association": "HJV",
    "Weight": 0.0,
    "Valid": false,
    "Gender": "male",
    "Paid": false
  },
  {
    "ID": 231,
    "Firstname": "Leon",
    "Lastname": "Wagner",
    "Name": "Leon Wagner",
    "Birthyear": 2017,
    "Club": "JC Hamburg Nord",
    "Association": "HJV",
    "Weight": 0.0,
    "Valid": false,
    "Gender": "male",
    "Paid": false
  },
  {
    "ID": 234,
    "Firstname": "Max",
    "Lastname": "Weber",
    "Name": "Max Weber",
    "Birthyear": 2001,
    "Club": "SV Potsdam",
    "Association": "JV Berlin",
    "Weight": 0.0,
    "Valid": false,
    "Gender": "male",
    "Paid": true
  },
  {
    "ID": 238,
    "Firstname": "Leon",
    "Lastname": "Meyer",
    "Name": "Leon Meyer",
    "Birthyear": 2012,
    "Club": "JC Leipzig",
    "Association": "JV Sachsen",
    "Weight": 0.0,
    "Valid": false,
    "Gender": "male",
    "Paid": true
  },
  {
    "ID": 240,
    "Firstname": "Jonas",
    "Lastname": "Fischer",
    "Name": "Jonas Fischer",
    "Birthyear": 2013,
    "Club": "Budosport Stuttgart",
    "Association": "WJV",
    "Weight": 0.0,
    "Valid": false,
    "Gender": "male",
    "Paid": true
  },
  {
    "ID": 242,
    "Firstname": "Tom",
    "Lastname": "Schäfer",
    "Name": "Tom Schäfer",
    "Birthyear": 2017,
    "Club": "Budosport Stuttgart",
    "Association": "WJV",
    "Weight": 0.0,
    "Valid": false,
    "Gender": "male",
    "Paid": true
  },
  {
    "ID": 244,
    "Firstname": "Ben",
    "Lastname": "Koch",
    "Name": "Ben Koch",
    "Birthyear": 2015,
    "Club": "JC Hamburg Nord",
    "Association": "HJV",
    "Weight": 0.0,
    "Valid": false,
    "Gender": "male",
    "Paid": false
  },
  {
    "ID": 245,
    "Firstname": "Max",
    "Lastname": "Weber",
    "Name": "Max Weber",
    "Birthyear": 2011,
    "Club": "PSV Frankfurt",
    "Association": "HJV",
    "Weight": 0.0,
    "Valid": false,
    "Gender": "male",
    "Paid": false
  },
  {
    "ID": 249,
    "Firstname": "Elias",
    "Lastname": "Koch",
    "Name": "Elias Koch",
    "Birthyear": 2007,
    "Club": "JC Leipzig",
    "Association": "JV Sachsen",
    "Weight": 0.0,
    "Valid": false,
    "Gender": "male",
    "Paid": true
  },
  {
    "ID": 250,
    "Firstname": "Elias",
    "Lastname": "Müller",
    "Name": "Elias Müller",
    "Birthyear": 2019,
    "Club": "Budosport Stuttgart",
    "Association": "WJV",
    "Weight": 0.0,
    "Valid": false,
    "Gender": "male",
    "Paid": true
  },
  {
    "ID": 256,
    "Firstname": "Ben",
    "Lastname": "Hoffmann",
    "Name": "Ben Hoffmann",
    "Birthyear": 2014,
    "Club": "MTV Karlsruhe",
    "Association": "BJV",
    "Weight": 0.0,
    "Valid": false,
    "Gender": "male",
    "Paid": false
  },
  {
    "ID": 264,
    "Firstname": "Leon",
    "Lastname": "Schmidt",
    "Name": "Leon Schmidt",
    "Birthyear": 2011,
    "Club": "JC München",
    "Association": "BJV",
    "Weight": 0.0,
    "Valid": false,
    "Gender": "male",
    "Paid": false
  },
  {
    "ID": 266,
    "Firstname": "Ben",
    "Lastname": "Koch",
    "Name": "Ben Koch",
    "Birthyear": 2018,
    "Club": "PSV Frankfurt",
    "Association": "HJV",
    "Weight": 0.0,
    "Valid": false,
    "Gender": "male",
    "Paid": false
  },
  {
    "ID": 267,
    "Firstname": "Finn",
    "Lastname": "Koch",
    "Name": "Finn Koch",
    "Birthyear": 2016,
    "Club": "JC Hamburg Nord",
    "Association": "HJV",
    "Weight": 0.0,
    "Valid": false,
    "Gender": "male",
    "Paid": true
  },
  {
    "ID": 271,
    "Firstname": "Ben",
    "Lastname": "Weber",
    "Name": "Ben Weber",
    "Birthyear": 2014,
    "Club": "JC Hamburg Nord",
    "Association": "HJV",
    "Weight": 0.0,
    "Valid": false,
    "Gender": "male",
    "Paid": false
  },
  {
    "ID": 272,
    "Firstname": "Leon",
    "Lastname": "Weber",
    "Name": "Leon Weber",
    "Birthyear": 2012,
    "Club": "SV Potsdam",
    "Association": "JV Berlin",
    "Weight": 0.0,
    "Valid": false,
    "Gender": "male",
    "Paid": false
  },
  {
    "ID": 273,
    "Firstname": "Elias",
    "Lastname": "Schmidt",
    "Name": "Elias Schmidt",
    "Birthyear": 2016,
    "Club": "TSV Köln",
    "Association": "NWJV",
    "Weight": 0.0,
    "Valid": false,
    "Gender": "male",
    "Paid": true
  },
  {
    "ID": 275,
    "Firstname": "Elias",
    "Lastname": "Wagner",
    "Name": "Elias Wagner",
    "Birthyear": 2007,
    "Club": "JC Hannover",
    "Association": "NJV",
    "Weight": 0.0,
    "Valid": false,
    "Gender": "male",
    "Paid": true
  },
  {
    "ID": 276,
    "Firstname": "Moritz",
    "Lastname": "Fischer",
    "Name": "Moritz Fischer",
    "Birthyear": 2016,
    "Club": "JC Berlin Süd",
    "Association": "JV Berlin",
    "Weight": 0.0,
    "Valid": false,
    "Gender": "male",
    "Paid": false
  },
  {
    "ID": 280,
    "Firstname": "Noah",
    "Lastname": "Hoffmann",
    "Name": "Noah Hoffmann",
    "Birthyear": 2015,
    "Club": "JC München",
    "Association": "BJV",
    "Weight": 0.0,
    "Valid": false,
    "Gender": "male",
    "Paid": true
  },
  {
    "ID": 282,
    "Firstname": "Tom",
    "Lastname": "Meyer",
    "Name": "Tom Meyer",
    "Birthyear": 2016,
    "Club": "JC Berlin Süd",
    "Association": "JV Berlin",
    "Weight": 0.0,
    "Valid": false,
    "Gender": "male",
    "Paid": true
  },
  {
    "ID": 283,
    "Firstname": "Jonas",
    "Lastname": "Wagner",
    "Name": "Jonas Wagner",
    "Birthyear": 2019,
    "Club": "JC München",
    "Association": "BJV",
    "Weight": 0.0,
    "Valid": false,
    "Gender": "male",
    "Paid": false
  },
  {
    "ID": 284,
    "Firstname": "Elias",
    "Lastname": "Hoffmann",
    "Name": "Elias Hoffmann",
    "Birthyear": 2010,
    "Club": "SV Potsdam",
    "Association": "JV Berlin",
    "Weight": 0.0,
    "Valid": false,
    "Gender": "male",
    "Paid": true
  },
  {
    "ID": 285,
    "Firstname": "Lukas",
    "Lastname": "Wagner",
    "Name": "Lukas Wagner",
    "Birthyear": 2017,
    "Club": "JC Hamburg Nord",
    "Association": "HJV",
    "Weight": 0.0,
    "Valid": false,
    "Gender": "male",
    "Paid": true
  },
  {
    "ID": 287,
    "Firstname": "Lukas",
    "Lastname": "Meyer",
    "Name": "Lukas Meyer",
    "Birthyear": 2009,
    "Club": "PSV Frankfurt",
    "Association": "HJV",
    "Weight": 0.0,
    "Valid": false,
    "Gender": "male",
    "Paid": true
  },
  {
    "ID": 296,
    "Firstname": "Lukas",
    "Lastname": "Koch",
    "Name": "Lukas Koch",
    "Birthyear": 2008,
    "Club": "PSV Frankfurt",
    "Association": "HJV",
    "Weight": 0.0,
    "Valid": false,
    "Gender": "male",
    "Paid": false
  },
  {
    "ID": 297,
    "Firstname": "Noah",
    "Lastname": "Wagner",
    "Name": "Noah Wagner",
    "Birthyear": 2004,
    "Club": "JC Hannover",
    "Association": "NJV",
    "Weight": 0.0,
    "Valid": false,
    "Gender": "male",
    "Paid": false
  },
  {
    "ID": 300,
    "Firstname": "Jonas",
    "Lastname": "Wagner",
    "Name": "Jonas Wagner",
    "Birthyear": 2012,
    "Club": "SV Potsdam",
    "Association": "JV Berlin",
    "Weight": 0.0,
    "Valid": false,
    "Gender": "male",
    "Paid": true
  },
  {
    "ID": 301,
    "Firstname": "Paul",
    "Lastname": "Becker",
    "Name": "Paul Becker",
    "Birthyear": 2011,
    "Club": "MTV Karlsruhe",
    "Association": "BJV",
    "Weight": 0.0,
    "Valid": false,
    "Gender": "male",
    "Paid": true
  },
  {
    "ID": 303,
    "Firstname": "Max",
    "Lastname": "Schneider",
    "Name": "Max Schneider",
    "Birthyear": 2014,
    "Club": "PSV Frankfurt",
    "Association": "HJV",
    "Weight": 0.0,
    "Valid": false,
    "Gender": "male",
    "Paid": true
  },
  {
    "ID": 304,
    "Firstname": "Leon",
    "Lastname": "Koch",
    "Name": "Leon Koch",
    "Birthyear": 2009,
    "Club": "SV Potsdam",
    "Association": "JV Berlin",
    "Weight": 0.0,
    "Valid": false,
    "Gender": "male",
    "Paid": true
  },
  {
    "ID": 307,
    "Firstname": "Tom",
    "Lastname": "Schmidt",
    "Name": "Tom Schmidt",
    "Birthyear": 2013,
    "Club": "JC München",
    "Association": "BJV",
    "Weight": 0.0,
    "Valid": false,
    "Gender": "male",
    "Paid": false
  },
  {
    "ID": 310,
    "Firstname": "Moritz",
    "Lastname": "Schmidt",
    "Name": "Moritz Schmidt",
    "Birthyear": 2015,
    "Club": "MTV Karlsruhe",
    "Association": "BJV",
    "Weight": 0.0,
    "Valid": false,
    "Gender": "male",
    "Paid": false
  },
  {
    "ID": 311,
    "Firstname": "Elias",
    "Lastname": "Becker",
    "Name": "Elias Becker",
    "Birthyear": 2001,
    "Club": "JC München",
    "Association": "BJV",
    "Weight": 0.0,
    "Valid": false,
    "Gender": "male",
    "Paid": false
  },
  {
    "ID": 315,
    "Firstname": "Tom",
    "Lastname": "Bauer",
    "Name": "Tom Bauer",
    "Birthyear": 2013,
    "Club": "JC Leipzig",
    "Association": "JV Sachsen",
    "Weight": 0.0,
    "Valid": false,
    "Gender": "male",
    "Paid": false
  },
  {
    "ID": 316,
    "Firstname": "Tom",
    "Lastname": "Weber",
    "Name": "Tom Weber",
    "Birthyear": 2011,
    "Club": "SV Potsdam",
    "Association": "JV Berlin",
    "Weight": 0.0,
    "Valid": false,
    "Gender": "male",
    "Paid": true
  },
  {
    "ID": 317,
    "Firstname": "Moritz",
    "Lastname": "Schneider",
    "Name": "Moritz Schneider",
    "Birthyear": 2016,
    "Club": "Budosport Stuttgart",
    "Association": "WJV",
    "Weight": 0.0,
    "Valid": false,
    "Gender": "male",
    "Paid": true
  },
  {
    "ID": 319,
    "Firstname": "Noah",
    "Lastname": "Koch",
    "Name": "Noah Koch",
    "Birthyear": 1995,
    "Club": "JC Hamburg Nord",
    "Association": "HJV",
    "Weight": 0.0,
    "Valid": false,
    "Gender": "male",
    "Paid": true
  },
  {
    "ID": 321,
    "Firstname": "Max",
    "Lastname": "Bauer",
    "Name": "Max Bauer",
    "Birthyear": 2015,
    "Club": "PSV Frankfurt",
    "Association": "HJV",
    "Weight": 0.0,
    "Valid": false,
    "Gender": "male",
    "Paid": true
  },
  {
    "ID": 326,
    "Firstname": "Ben",
    "Lastname": "Hoffmann",
    "Name": "Ben Hoffmann",
    "Birthyear": 2015,
    "Club": "PSV Frankfurt",
    "Association": "HJV",
    "Weight": 0.0,
    "Valid": false,
    "Gender": "male",
    "Paid": true
  },
  {
    "ID": 327,
    "Firstname": "Leon",
    "Lastname": "Becker",
    "Name": "Leon Becker",
    "Birthyear": 2008,
    "Club": "MTV Karlsruhe",
    "Association": "BJV",
    "Weight": 0.0,
    "Valid": false,
    "Gender": "male",
    "Paid": true
  },
  {
    "ID": 330,
    "Firstname": "Finn",
    "Lastname": "Becker",
    "Name": "Finn Becker",
    "Birthyear": 2018,
    "Club": "TSV Köln",
    "Association": "NWJV",
    "Weight": 0.0,
    "Valid": false,
    "Gender": "male",
    "Paid": false
  },
  {
    "ID": 333,
    "Firstname": "Noah",
    "Lastname": "Schmidt",
    "Name": "Noah Schmidt",
    "Birthyear": 2013,
    "Club": "JC Leipzig",
    "Association": "JV Sachsen",
    "Weight": 0.0,
    "Valid": false,
    "Gender": "male",
    "Paid": false
  },
  {
    "ID": 335,
    "Firstname": "Lukas",
    "Lastname": "Meyer",
    "Name": "Lukas Meyer",
    "Birthyear": 2014,
    "Club": "MTV Karlsruhe",
    "Association": "BJV",
    "Weight": 0.0,
    "Valid": false,
    "Gender": "male",
    "Paid": false
  },
  {
    "ID": 337,
    "Firstname": "Leon",
    "Lastname": "Meyer",
    "Name": "Leon Meyer",
    "Birthyear": 2013,
    "Club": "JC Hamburg Nord",
    "Association": "HJV",
    "Weight": 0.0,
    "Valid": false,
    "Gender": "male",
    "Paid": false
  },
  {
    "ID": 339,
    "Firstname": "Jonas",
    "Lastname": "Müller",
    "Name": "Jonas Müller",
    "Birthyear": 2011,
    "Club": "PSV Frankfurt",
    "Association": "HJV",
    "Weight": 0.0,
    "Valid": false,
    "Gender": "male",
    "Paid": true
  },
  {
    "ID": 341,
    "Firstname": "Paul",
    "Lastname": "Schneider",
    "Name": "Paul Schneider",
    "Birthyear": 2013,
    "Club": "MTV Karlsruhe",
    "Association": "BJV",
    "Weight": 0.0,
    "Valid": false,
    "Gender": "male",
    "Paid": false
  },
  {
    "ID": 343,
    "Firstname": "Paul",
    "Lastname": "Weber",
    "Name": "Paul Weber",
    "Birthyear": 1999,
    "Club": "PSV Frankfurt",
    "Association": "HJV",
    "Weight": 0.0,
    "Valid": false,
    "Gender": "male",
    "Paid": true
  },
  {
    "ID": 344,
    "Firstname": "Noah",
    "Lastname": "Bauer",
    "Name": "Noah Bauer",
    "Birthyear": 2018,
    "Club": "PSV Frankfurt",
    "Association": "HJV",
    "Weight": 0.0,
    "Valid": false,
    "Gender": "male",
    "Paid": false
  },
  {
    "ID": 346,
    "Firstname": "Tom",
    "Lastname": "Hoffmann",
    "Name": "Tom Hoffmann",
    "Birthyear": 2012,
    "Club": "Budosport Stuttgart",
    "Association": "WJV",
    "Weight": 0.0,
    "Valid": false,
    "Gender": "male",
    "Paid": false
  },
  {
    "ID": 347,
    "Firstname": "Tom",
    "Lastname": "Weber",
    "Name": "Tom Weber",
    "Birthyear": 2015,
    "Club": "JC Hannover",
    "Association": "NJV",
    "Weight": 0.0,
    "Valid": false,
    "Gender": "male",
    "Paid": true
  },
  {
    "ID": 348,
    "Firstname": "Paul",
    "Lastname": "Koch",
    "Name": "Paul Koch",
    "Birthyear": 2001,
    "Club": "JC Leipzig",
    "Association": "JV Sachsen",
    "Weight": 0.0,
    "Valid": false,
    "Gender": "male",
    "Paid": true
  },
  {
    "ID": 352,
    "Firstname": "Paul",
    "Lastname": "Wagner",
    "Name": "Paul Wagner",
    "Birthyear": 2012,
    "Club": "MTV Karlsruhe",
    "Association": "BJV",
    "Weight": 0.0,
    "Valid": false,
    "Gender": "male",
    "Paid": true
  },
  {
    "ID": 353,
    "Firstname": "Ben",
    "Lastname": "Fischer",
    "Name": "Ben Fischer",
    "Birthyear": 2014,
    "Club": "TSV Köln",
    "Association": "NWJV",
    "Weight": 0.0,
    "Valid": false,
    "Gender": "male",
    "Paid": false
  },
  {
    "ID": 356,
    "Firstname": "Tim",
    "Lastname": "Meyer",
    "Name": "Tim Meyer",
    "Birthyear": 2012,
    "Club": "JC München",
    "Association": "BJV",
    "Weight": 0.0,
    "Valid": false,
    "Gender": "male",
    "Paid": true
  },
  {
    "ID": 357,
    "Firstname": "Moritz",
    "Lastname": "Meyer",
    "Name": "Moritz Meyer",
    "Birthyear": 2006,
    "Club": "TSV Köln",
    "Association": "NWJV",
    "Weight": 0.0,
    "Valid": false,
    "Gender": "male",
    "Paid": false
  },
  {
    "ID": 358,
    "Firstname": "Tom",
    "Lastname": "Bauer",
    "Name": "Tom Bauer",
    "Birthyear": 2017,
    "Club": "JC Leipzig",
    "Association": "JV Sachsen",
    "Weight": 0.0,
    "Valid": false,
    "Gender": "male",
    "Paid": false
  },
  {
    "ID": 360,
    "Firstname": "Tim",
    "Lastname": "Schäfer",
    "Name": "Tim Schäfer",
    "Birthyear": 2013,
    "Club": "JC München",
    "Association": "BJV",
    "Weight": 0.0,
    "Valid": false,
    "Gender": "male",
    "Paid": false
  },
  {
    "ID": 361,
    "Firstname": "Moritz",
    "Lastname": "Wagner",
    "Name": "Moritz Wagner",
    "Birthyear": 2014,
    "Club": "SV Potsdam",
    "Association": "JV Berlin",
    "Weight": 0.0,
    "Valid": false,
    "Gender": "male",
    "Paid": false
  },
  {
    "ID": 362,
    "Firstname": "Ben",
    "Lastname": "Schäfer",
    "Name": "Ben Schäfer",
    "Birthyear": 2014,
    "Club": "TSV Köln",
    "Association": "NWJV",
    "Weight": 0.0,
    "Valid": false,
    "Gender": "male",
    "Paid": true
  },
  {
    "ID": 363,
    "Firstname": "Ben",
    "Lastname": "Schmidt",
    "Name": "Ben Schmidt",
    "Birthyear": 2012,
    "Club": "JC Berlin Süd",
    "Association": "JV Berlin",
    "Weight": 0.0,
    "Valid": false,
    "Gender": "male",
    "Paid": false
  },
  {
    "ID": 365,
    "Firstname": "Noah",
    "Lastname": "Schneider",
    "Name": "Noah Schneider",
    "Birthyear": 2008,
    "Club": "JC Berlin Süd",
    "Association": "JV Berlin",
    "Weight": 0.0,
    "Valid": false,
    "Gender": "male",
    "Paid": false
  },
  {
    "ID": 366,
    "Firstname": "Elias",
    "Lastname": "Schmidt",
    "Name": "Elias Schmidt",
    "Birthyear": 2011,
    "Club": "JC Hamburg Nord",
    "Association": "HJV",
    "Weight": 0.0,
    "Valid": false,
    "Gender": "male",
    "Paid": true
  },
  {
    "ID": 373,
    "Firstname": "Paul",
    "Lastname": "Becker",
    "Name": "Paul Becker",
    "Birthyear": 2011,
    "Club": "JC München",
    "Association": "BJV",
    "Weight": 0.0,
    "Valid": false,
    "Gender": "male",
    "Paid": true
  },
  {
    "ID": 375,
    "Firstname": "Noah",
    "Lastname": "Wagner",
    "Name": "Noah Wagner",
    "Birthyear": 2005,
    "Club": "PSV Frankfurt",
    "Association": "HJV",
    "Weight": 0.0,
    "Valid": false,
    "Gender": "male",
    "Paid": false
  },
  {
    "ID": 378,
    "Firstname": "Ben",
    "Lastname": "Becker",
    "Name": "Ben Becker",
    "Birthyear": 1998,
    "Club": "JC Berlin Süd",
    "Association": "JV Berlin",
    "Weight": 0.0,
    "Valid": false,
    "Gender": "male",
    "Paid": false
  },
  {
    "ID": 379,
    "Firstname": "Ben",
    "Lastname": "Schmidt",
    "Name": "Ben Schmidt",
    "Birthyear": 2011,
    "Club": "Budosport Stuttgart",
    "Association": "WJV",
    "Weight": 0.0,
    "Valid": false,
    "Gender": "male",
    "Paid": false
  },
  {
    "ID": 380,
    "Firstname": "Tim",
    "Lastname": "Fischer",
    "Name": "Tim Fischer",
    "Birthyear": 2011,
    "Club": "MTV Karlsruhe",
    "Association": "BJV",
    "Weight": 0.0,
    "Valid": false,
    "Gender": "male",
    "Paid": false
  },
  {
    "ID": 382,
    "Firstname": "Noah",
    "Lastname": "Fischer",
    "Name": "Noah Fischer",
    "Birthyear": 2015,
    "Club": "Budosport Stuttgart",
    "Association": "WJV",
    "Weight": 0.0,
    "Valid": false,
    "Gender": "male",
    "Paid": true
  },
  {
    "ID": 383,
    "Firstname": "Jonas",
    "Lastname": "Fischer",
    "Name": "Jonas Fischer",
    "Birthyear": 2016,
    "Club": "JC Berlin Süd",
    "Association": "JV Berlin",
    "Weight": 0.0,
    "Valid": false,
    "Gender": "male",
    "Paid": false
  },
  {
    "ID": 385,
    "Firstname": "Ben",
    "Lastname": "Hoffmann",
    "Name": "Ben Hoffmann",
    "Birthyear": 2016,
    "Club": "JC Berlin Süd",
    "Association": "JV Berlin",
    "Weight": 0.0,
    "Valid": false,
    "Gender": "male",
    "Paid": true
  },
  {
    "ID": 388,
    "Firstname": "Ben",
    "Lastname": "Wagner",
    "Name": "Ben Wagner",
    "Birthyear": 1995,
    "Club": "JC München",
    "Association": "BJV",
    "Weight": 0.0,
    "Valid": false,
    "Gender": "male",
    "Paid": true
  },
  {
    "ID": 389,
    "Firstname": "Lukas",
    "Lastname": "Wagner",
    "Name": "Lukas Wagner",
    "Birthyear": 2013,
    "Club": "JC Hamburg Nord",
    "Association": "HJV",
    "Weight": 0.0,
    "Valid": false,
    "Gender": "male",
    "Paid": false
  },
  {
    "ID": 391,
    "Firstname": "Lukas",
    "Lastname": "Wagner",
    "Name": "Lukas Wagner",
    "Birthyear": 2013,
    "Club": "MTV Karlsruhe",
    "Association": "BJV",
    "Weight": 0.0,
    "Valid": false,
    "Gender": "male",
    "Paid": true
  },
  {
    "ID": 392,
    "Firstname": "Elias",
    "Lastname": "Schmidt",
    "Name": "Elias Schmidt",
    "Birthyear": 2015,
    "Club": "SV Potsdam",
    "Association": "JV Berlin",
    "Weight": 0.0,
    "Valid": false,
    "Gender": "male",
    "Paid": true
  },
  {
    "ID": 399,
    "Firstname": "Jonas",
    "Lastname": "Becker",
    "Name": "Jonas Becker",
    "Birthyear": 2014,
    "Club": "JC Leipzig",
    "Association": "JV Sachsen",
    "Weight": 0.0,
    "Valid": false,
    "Gender": "male",
    "Paid": false
  },
  {
    "ID": 400,
    "Firstname": "Paul",
    "Lastname": "Meyer",
    "Name": "Paul Meyer",
    "Birthyear": 2014,
    "Club": "JC Berlin Süd",
    "Association": "JV Berlin",
    "Weight": 0.0,
    "Valid": false,
    "Gender": "male",
    "Paid": false
  },
  {
    "ID": 402,
    "Firstname": "Elias",
    "Lastname": "Becker",
    "Name": "Elias Becker",
    "Birthyear": 2018,
    "Club": "JC München",
    "Association": "BJV",
    "Weight": 0.0,
    "Valid": false,
    "Gender": "male",
    "Paid": true
  },
  {
    "ID": 403,
    "Firstname": "Lukas",
    "Lastname": "Koch",
    "Name": "Lukas Koch",
    "Birthyear": 2012,
    "Club": "PSV Frankfurt",
    "Association": "HJV",
    "Weight": 0.0,
    "Valid": false,
    "Gender": "male",
    "Paid": true
  },
  {
    "ID": 406,
    "Firstname": "Max",
    "Lastname": "Fischer",
    "Name": "Max Fischer",
    "Birthyear": 2013,
    "Club": "JC Leipzig",
    "Association": "JV Sachsen",
    "Weight": 0.0,
    "Valid": false,
    "Gender": "male",
    "Paid": false
  },
  {
    "ID": 407,
    "Firstname": "Moritz",
    "Lastname": "Fischer",
    "Name": "Moritz Fischer",
    "Birthyear": 2008,
    "Club": "Budosport Stuttgart",
    "Association": "WJV",
    "Weight": 0.0,
    "Valid": false,
    "Gender": "male",
    "Paid": false
  },
  {
    "ID": 408,
    "Firstname": "Lukas",
    "Lastname": "Koch",
    "Name": "Lukas Koch",
    "Birthyear": 1996,
    "Club": "TSV Köln",
    "Association": "NWJV",
    "Weight": 0.0,
    "Valid": false,
    "Gender": "male",
    "Paid": true
  },
  {
    "ID": 409,
    "Firstname": "Elias",
    "Lastname": "Weber",
    "Name": "Elias Weber",
    "Birthyear": 2017,
    "Club": "JC Hamburg Nord",
    "Association": "HJV",
    "Weight": 0.0,
    "Valid": false,
    "Gender": "male",
    "Paid": true
  },
  {
    "ID": 411,
    "Firstname": "Elias",
    "Lastname": "Weber",
    "Name": "Elias Weber",
    "Birthyear": 2015,
    "Club": "MTV Karlsruhe",
    "Association": "BJV",
    "Weight": 0.0,
    "Valid": false,
    "Gender": "male",
    "Paid": false
  },
  {
    "ID": 412,
    "Firstname": "Paul",
    "Lastname": "Meyer",
    "Name": "Paul Meyer",
    "Birthyear": 2008,
    "Club": "JC Leipzig",
    "Association": "JV Sachsen",
    "Weight": 0.0,
    "Valid": false,
    "Gender": "male",
    "Paid": true
  },
  {
    "ID": 414,
    "Firstname": "Leon",
    "Lastname": "Müller",
    "Name": "Leon Müller",
    "Birthyear": 2014,
    "Club": "MTV Karlsruhe",
    "Association": "BJV",
    "Weight": 0.0,
    "Valid": false,
    "Gender": "male",
    "Paid": false
  },
  {
    "ID": 415,
    "Firstname": "Leon",
    "Lastname": "Weber",
    "Name": "Leon Weber",
    "Birthyear": 2008,
    "Club": "SV Potsdam",
    "Association": "JV Berlin",
    "Weight": 0.0,
    "Valid": false,
    "Gender": "male",
    "Paid": false
  },
  {
    "ID": 416,
    "Firstname": "Leon",
    "Lastname": "Schmidt",
    "Name": "Leon Schmidt",
    "Birthyear": 2009,
    "Club": "TSV Köln",
    "Association": "NWJV",
    "Weight": 0.0,
    "Valid": false,
    "Gender": "male",
    "Paid": true
  },
  {
    "ID": 417,
    "Firstname": "Elias",
    "Lastname": "Wagner",
    "Name": "Elias Wagner",
    "Birthyear": 2017,
    "Club": "JC Berlin Süd",
    "Association": "JV Berlin",
    "Weight": 0.0,
    "Valid": false,
    "Gender": "male",
    "Paid": false
  },
  {
    "ID": 419,
    "Firstname": "Jonas",
    "Lastname": "Schmidt",
    "Name": "Jonas Schmidt",
    "Birthyear": 2014,
    "Club": "SV Potsdam",
    "Association": "JV Berlin",
    "Weight": 0.0,
    "Valid": false,
    "Gender": "male",
    "Paid": true
  },
  {
    "ID": 422,
    "Firstname": "Finn",
    "Lastname": "Meyer",
    "Name": "Finn Meyer",
    "Birthyear": 2017,
    "Club": "JC München",
    "Association": "BJV",
    "Weight": 0.0,
    "Valid": false,
    "Gender": "male",
    "Paid": true
  },
  {
    "ID": 423,
    "Firstname": "Elias",
    "Lastname": "Schneider",
    "Name": "Elias Schneider",
    "Birthyear": 1995,
    "Club": "Budosport Stuttgart",
    "Association": "WJV",
    "Weight": 0.0,
    "Valid": false,
    "Gender": "male",
    "Paid": false
  },
  {
    "ID": 424,
    "Firstname": "Moritz",
    "Lastname": "Koch",
    "Name": "Moritz Koch",
    "Birthyear": 2011,
    "Club": "SV Potsdam",
    "Association": "JV Berlin",
    "Weight": 0.0,
    "Valid": false,
    "Gender": "male",
    "Paid": false
  },
  {
    "ID": 425,
    "Firstname": "Finn",
    "Lastname": "Müller",
    "Name": "Finn Müller",
    "Birthyear": 2012,
    "Club": "MTV Karlsruhe",
    "Association": "BJV",
    "Weight": 0.0,
    "Valid": false,
    "Gender": "male",
    "Paid": false
  },
  {
    "ID": 426,
    "Firstname": "Tom",
    "Lastname": "Bauer",
    "Name": "Tom Bauer",
    "Birthyear": 2012,
    "Club": "JC Hamburg Nord",
    "Association": "HJV",
    "Weight": 0.0,
    "Valid": false,
    "Gender": "male",
    "Paid": false
  },
  {
    "ID": 431,
    "Firstname": "Paul",
    "Lastname": "Schmidt",
    "Name": "Paul Schmidt",
    "Birthyear": 2014,
    "Club": "JC Hamburg Nord",
    "Association": "HJV",
    "Weight": 0.0,
    "Valid": false,
    "Gender": "male",
    "Paid": true
  },
  {
    "ID": 432,
    "Firstname": "Paul",
    "Lastname": "Schneider",
    "Name": "Paul Schneider",
    "Birthyear": 2015,
    "Club": "TSV Köln",
    "Association": "NWJV",
    "Weight": 0.0,
    "Valid": false,
    "Gender": "male",
    "Paid": false
  },
  {
    "ID": 438,
    "Firstname": "Moritz",
    "Lastname": "Bauer",
    "Name": "Moritz Bauer",
    "Birthyear": 2005,
    "Club": "JC Hannover",
    "Association": "NJV",
    "Weight": 0.0,
    "Valid": false,
    "Gender": "male",
    "Paid": false
  },
  {
    "ID": 440,
    "Firstname": "Tim",
    "Lastname": "Müller",
    "Name": "Tim Müller",
    "Birthyear": 2013,
    "Club": "Budosport Stuttgart",
    "Association": "WJV",
    "Weight": 0.0,
    "Valid": false,
    "Gender": "male",
    "Paid": false
  },
  {
    "ID": 442,
    "Firstname": "Ben",
    "Lastname": "Becker",
    "Name": "Ben Becker",
    "Birthyear": 2013,
    "Club": "JC Hamburg Nord",
    "Association": "HJV",
    "Weight": 0.0,
    "Valid": false,
    "Gender": "male",
    "Paid": false
  },
  {
    "ID": 446,
    "Firstname": "Tim",
    "Lastname": "Müller",
    "Name": "Tim Müller",
    "Birthyear": 2015,
    "Club": "JC Hamburg Nord",
    "Association": "HJV",
    "Weight": 0.0,
    "Valid": false,
    "Gender": "male",
    "Paid": false
  },
  {
    "ID": 447,
    "Firstname": "Elias",
    "Lastname": "Koch",
    "Name": "Elias Koch",
    "Birthyear": 1998,
    "Club": "JC Hamburg Nord",
    "Association": "HJV",
    "Weight": 0.0,
    "Valid": false,
    "Gender": "male",
    "Paid": false
  },
  {
    "ID": 452,
    "Firstname": "Max",
    "Lastname": "Meyer",
    "Name": "Max Meyer",
    "Birthyear": 2010,
    "Club": "TSV Köln",
    "Association": "NWJV",
    "Weight": 0.0,
    "Valid": false,
    "Gender": "male",
    "Paid": false
  },
  {
    "ID": 458,
    "Firstname": "Lukas",
    "Lastname": "Hoffmann",
    "Name": "Lukas Hoffmann",
    "Birthyear": 2009,
    "Club": "Budosport Stuttgart",
    "Association": "WJV",
    "Weight": 0.0,
    "Valid": false,
    "Gender": "male",
    "Paid": true
  },
  {
    "ID": 459,
    "Firstname": "Elias",
    "Lastname": "Müller",
    "Name": "Elias Müller",
    "Birthyear": 2011,
    "Club": "TSV Köln",
    "Association": "NWJV",
    "Weight": 0.0,
    "Valid": false,
    "Gender": "male",
    "Paid": true
  },
  {
    "ID": 464,
    "Firstname": "Noah",
    "Lastname": "Müller",
    "Name": "Noah Müller",
    "Birthyear": 2018,
    "Club": "JC Berlin Süd",
    "Association": "JV Berlin",
    "Weight": 0.0,
    "Valid": false,
    "Gender": "male",
    "Paid": true
  },
  {
    "ID": 465,
    "Firstname": "Lukas",
    "Lastname": "Meyer",
    "Name": "Lukas Meyer",
    "Birthyear": 2015,
    "Club": "Budosport Stuttgart",
    "Association": "WJV",
    "Weight": 0.0,
    "Valid": false,
    "Gender": "male",
    "Paid": false
  },
  {
    "ID": 468,
    "Firstname": "Max",
    "Lastname": "Müller",
    "Name": "Max Müller",
    "Birthyear": 2016,
    "Club": "SV Potsdam",
    "Association": "JV Berlin",
    "Weight": 0.0,
    "Valid": false,
    "Gender": "male",
    "Paid": false
  },
  {
    "ID": 470,
    "Firstname": "Noah",
    "Lastname": "Schmidt",
    "Name": "Noah Schmidt",
    "Birthyear": 2018,
    "Club": "JC Hamburg Nord",
    "Association": "HJV",
    "Weight": 0.0,
    "Valid": false,
    "Gender": "male",
    "Paid": false
  },
  {
    "ID": 472,
    "Firstname": "Max",
    "Lastname": "Wagner",
    "Name": "Max Wagner",
    "Birthyear": 2009,
    "Club": "MTV Karlsruhe",
    "Association": "BJV",
    "Weight": 0.0,
    "Valid": false,
    "Gender": "male",
    "Paid": false
  },
  {
    "ID": 473,
    "Firstname": "Paul",
    "Lastname": "Bauer",
    "Name": "Paul Bauer",
    "Birthyear": 2011,
    "Club": "SV Potsdam",
    "Association": "JV Berlin",
    "Weight": 0.0,
    "Valid": false,
    "Gender": "male",
    "Paid": false
  },
  {
    "ID": 475,
    "Firstname": "Leon",
    "Lastname": "Bauer",
    "Name": "Leon Bauer",
    "Birthyear": 2014,
    "Club": "JC Hannover",
    "Association": "NJV",
    "Weight": 0.0,
    "Valid": false,
    "Gender": "male",
    "Paid": false
  },
  {
    "ID": 476,
    "Firstname": "Finn",
    "Lastname": "Bauer",
    "Name": "Finn Bauer",
    "Birthyear": 2014,
    "Club": "Budosport Stuttgart",
    "Association": "WJV",
    "Weight": 0.0,
    "Valid": false,
    "Gender": "male",
    "Paid": false
  },
  {
    "ID": 477,
    "Firstname": "Jonas",
    "Lastname": "Schneider",
    "Name": "Jonas Schneider",
    "Birthyear": 2012,
    "Club": "JC Berlin Süd",
    "Association": "JV Berlin",
    "Weight": 0.0,
    "Valid": false,
    "Gender": "male",
    "Paid": true
  },
  {
    "ID": 480,
    "Firstname": "Tim",
    "Lastname": "Hoffmann",
    "Name": "Tim Hoffmann",
    "Birthyear": 2013,
    "Club": "Budosport Stuttgart",
    "Association": "WJV",
    "Weight": 0.0,
    "Valid": false,
    "Gender": "male",
    "Paid": false
  },
  {
    "ID": 481,
    "Firstname": "Elias",
    "Lastname": "Schneider",
    "Name": "Elias Schneider",
    "Birthyear": 2011,
    "Club": "Budosport Stuttgart",
    "Association": "WJV",
    "Weight": 0.0,
    "Valid": false,
    "Gender": "male",
    "Paid": false
  },
  {
    "ID": 482,
    "Firstname": "Ben",
    "Lastname": "Bauer",
    "Name": "Ben Bauer",
    "Birthyear": 2015,
    "Club": "Budosport Stuttgart",
    "Association": "WJV",
    "Weight": 0.0,
    "Valid": false,
    "Gender": "male",
    "Paid": true
  },
  {
    "ID": 484,
    "Firstname": "Max",
    "Lastname": "Becker",
    "Name": "Max Becker",
    "Birthyear": 2018,
    "Club": "PSV Frankfurt",
    "Association": "HJV",
    "Weight": 0.0,
    "Valid": false,
    "Gender": "male",
    "Paid": true
  },
  {
    "ID": 485,
    "Firstname": "Moritz",
    "Lastname": "Schmidt",
    "Name": "Moritz Schmidt",
    "Birthyear": 2014,
    "Club": "JC München",
    "Association": "BJV",
    "Weight": 0.0,
    "Valid": false,
    "Gender": "male",
    "Paid": false
  },
  {
    "ID": 486,
    "Firstname": "Moritz",
    "Lastname": "Schäfer",
    "Name": "Moritz Schäfer",
    "Birthyear": 2005,
    "Club": "SV Potsdam",
    "Association": "JV Berlin",
    "Weight": 0.0,
    "Valid": false,
    "Gender": "male",
    "Paid": false
  },
  {
    "ID": 487,
    "Firstname": "Paul",
    "Lastname": "Meyer",
    "Name": "Paul Meyer",
    "Birthyear": 2016,
    "Club": "SV Potsdam",
    "Association": "JV Berlin",
    "Weight": 0.0,
    "Valid": false,
    "Gender": "male",
    "Paid": true
  },
  {
    "ID": 490,
    "Firstname": "Noah",
    "Lastname": "Schäfer",
    "Name": "Noah Schäfer",
    "Birthyear": 2012,
    "Club": "MTV Karlsruhe",
    "Association": "BJV",
    "Weight": 0.0,
    "Valid": false,
    "Gender": "male",
    "Paid": true
  },
  {
    "ID": 491,
    "Firstname": "Leon",
    "Lastname": "Wagner",
    "Name": "Leon Wagner",
    "Birthyear": 2013,
    "Club": "PSV Frankfurt",
    "Association": "HJV",
    "Weight": 0.0,
    "Valid": false,
    "Gender": "male",
    "Paid": true
  },
  {
    "ID": 492,
    "Firstname": "Tom",
    "Lastname": "Fischer",
    "Name": "Tom Fischer",
    "Birthyear": 2018,
    "Club": "PSV Frankfurt",
    "Association": "HJV",
    "Weight": 0.0,
    "Valid": false,
    "Gender": "male",
    "Paid": false
  },
  {
    "ID": 496,
    "Firstname": "Jonas",
    "Lastname": "Bauer",
    "Name": "Jonas Bauer",
    "Birthyear": 2016,
    "Club": "PSV Frankfurt",
    "Association": "HJV",
    "Weight": 0.0,
    "Valid": false,
    "Gender": "male",
    "Paid": false
  },
  {
    "ID": 498,
    "Firstname": "Noah",
    "Lastname": "Meyer",
    "Name": "Noah Meyer",
    "Birthyear": 2001,
    "Club": "PSV Frankfurt",
    "Association": "HJV",
    "Weight": 0.0,
    "Valid": false,
    "Gender": "male",
    "Paid": true
  },
  {
    "ID": 500,
    "Firstname": "Tom",
    "Lastname": "Schneider",
    "Name": "Tom Schneider",
    "Birthyear": 2011,
    "Club": "JC Berlin Süd",
    "Association": "JV Berlin",
    "Weight": 0.0,
    "Valid": false,
    "Gender": "male",
    "Paid": true
  },
  {
    "ID": 501,
    "Firstname": "Leon",
    "Lastname": "Schneider",
    "Name": "Leon Schneider",
    "Birthyear": 2012,
    "Club": "SV Potsdam",
    "Association": "JV Berlin",
    "Weight": 0.0,
    "Valid": false,
    "Gender": "male",
    "Paid": true
  },
  {
    "ID": 502,
    "Firstname": "Max",
    "Lastname": "Weber",
    "Name": "Max Weber",
    "Birthyear": 2011,
    "Club": "Budosport Stuttgart",
    "Association": "WJV",
    "Weight": 0.0,
    "Valid": false,
    "Gender": "male",
    "Paid": true
  },
  {
    "ID": 503,
    "Firstname": "Paul",
    "Lastname": "Fischer",
    "Name": "Paul Fischer",
    "Birthyear": 2010,
    "Club": "Budosport Stuttgart",
    "Association": "WJV",
    "Weight": 0.0,
    "Valid": false,
    "Gender": "male",
    "Paid": false
  },
  {
    "ID": 505,
    "Firstname": "Lukas",
    "Lastname": "Wagner",
    "Name": "Lukas Wagner",
    "Birthyear": 2014,
    "Club": "PSV Frankfurt",
    "Association": "HJV",
    "Weight": 0.0,
    "Valid": false,
    "Gender": "male",
    "Paid": true
  },
  {
    "ID": 506,
    "Firstname": "Noah",
    "Lastname": "Bauer",
    "Name": "Noah Bauer",
    "Birthyear": 1996,
    "Club": "JC München",
    "Association": "BJV",
    "Weight": 0.0,
    "Valid": false,
    "Gender": "male",
    "Paid": true
  },
  {
    "ID": 509,
    "Firstname": "Max",
    "Lastname": "Müller",
    "Name": "Max Müller",
    "Birthyear": 2013,
    "Club": "JC Berlin Süd",
    "Association": "JV Berlin",
    "Weight": 0.0,
    "Valid": false,
    "Gender": "male",
    "Paid": true
  },
  {
    "ID": 510,
    "Firstname": "Elias",
    "Lastname": "Wagner",
    "Name": "Elias Wagner",
    "Birthyear": 2000,
    "Club": "JC München",
    "Association": "BJV",
    "Weight": 0.0,
    "Valid": false,
    "Gender": "male",
    "Paid": false
  },
  {
    "ID": 511,
    "Firstname": "Elias",
    "Lastname": "Weber",
    "Name": "Elias Weber",
    "Birthyear": 2008,
    "Club": "JC Hamburg Nord",
    "Association": "HJV",
    "Weight": 0.0,
    "Valid": false,
    "Gender": "male",
    "Paid": false
  },
  {
    "ID": 513,
    "Firstname": "Ben",
    "Lastname": "Wagner",
    "Name": "Ben Wagner",
    "Birthyear": 2013,
    "Club": "JC Berlin Süd",
    "Association": "JV Berlin",
    "Weight": 0.0,
    "Valid": false,
    "Gender": "male",
    "Paid": true
  },
  {
    "ID": 514,
    "Firstname": "Ben",
    "Lastname": "Schmidt",
    "Name": "Ben Schmidt",
    "Birthyear": 2011,
    "Club": "SV Potsdam",
    "Association": "JV Berlin",
    "Weight": 0.0,
    "Valid": false,
    "Gender": "male",
    "Paid": false
  },
  {
    "ID": 515,
    "Firstname": "Elias",
    "Lastname": "Schmidt",
    "Name": "Elias Schmidt",
    "Birthyear": 2012,
    "Club": "Budosport Stuttgart",
    "Association": "WJV",
    "Weight": 0.0,
    "Valid": false,
    "Gender": "male",
    "Paid": true
  },
  {
    "ID": 516,
    "Firstname": "Finn",
    "Lastname": "Schäfer",
    "Name": "Finn Schäfer",
    "Birthyear": 2011,
    "Club": "Budosport Stuttgart",
    "Association": "WJV",
    "Weight": 0.0,
    "Valid": false,
    "Gender": "male",
    "Paid": true
  },
  {
    "ID": 520,
    "Firstname": "Max",
    "Lastname": "Becker",
    "Name": "Max Becker",
    "Birthyear": 2015,
    "Club": "JC München",
    "Association": "BJV",
    "Weight": 0.0,
    "Valid": false,
    "Gender": "male",
    "Paid": true
  },
  {
    "ID": 521,
    "Firstname": "Lukas",
    "Lastname": "Schneider",
    "Name": "Lukas Schneider",
    "Birthyear": 1996,
    "Club": "PSV Frankfurt",
    "Association": "HJV",
    "Weight": 0.0,
    "Valid": false,
    "Gender": "male",
    "Paid": false
  },
  {
    "ID": 524,
    "Firstname": "Lukas",
    "Lastname": "Schmidt",
    "Name": "Lukas Schmidt",
    "Birthyear": 2014,
    "Club": "Budosport Stuttgart",
    "Association": "WJV",
    "Weight": 0.0,
    "Valid": false,
    "Gender": "male",
    "Paid": true
  },
  {
    "ID": 525,
    "Firstname": "Tom",
    "Lastname": "Koch",
    "Name": "Tom Koch",
    "Birthyear": 2017,
    "Club": "SV Potsdam",
    "Association": "JV Berlin",
    "Weight": 0.0,
    "Valid": false,
    "Gender": "male",
    "Paid": false
  },
  {
    "ID": 530,
    "Firstname": "Leon",
    "Lastname": "Meyer",
    "Name": "Leon Meyer",
    "Birthyear": 2009,
    "Club": "MTV Karlsruhe",
    "Association": "BJV",
    "Weight": 0.0,
    "Valid": false,
    "Gender": "male",
    "Paid": true
  },
  {
    "ID": 532,
    "Firstname": "Finn",
    "Lastname": "Schneider",
    "Name": "Finn Schneider",
    "Birthyear": 1996,
    "Club": "JC Hannover",
    "Association": "NJV",
    "Weight": 0.0,
    "Valid": false,
    "Gender": "male",
    "Paid": false
  },
  {
    "ID": 533,
    "Firstname": "Max",
    "Lastname": "Bauer",
    "Name": "Max Bauer",
    "Birthyear": 1995,
    "Club": "PSV Frankfurt",
    "Association": "HJV",
    "Weight": 0.0,
    "Valid": false,
    "Gender": "male",
    "Paid": false
  },
  {
    "ID": 535,
    "Firstname": "Finn",
    "Lastname": "Wagner",
    "Name": "Finn Wagner",
    "Birthyear": 2014,
    "Club": "MTV Karlsruhe",
    "Association": "BJV",
    "Weight": 0.0,
    "Valid": false,
    "Gender": "male",
    "Paid": false
  },
  {
    "ID": 536,
    "Firstname": "Jonas",
    "Lastname": "Meyer",
    "Name": "Jonas Meyer",
    "Birthyear": 2015,
    "Club": "SV Potsdam",
    "Association": "JV Berlin",
    "Weight": 0.0,
    "Valid": false,
    "Gender": "male",
    "Paid": true
  },
  {
    "ID": 537,
    "Firstname": "Moritz",
    "Lastname": "Hoffmann",
    "Name": "Moritz Hoffmann",
    "Birthyear": 2013,
    "Club": "JC München",
    "Association": "BJV",
    "Weight": 0.0,
    "Valid": false,
    "Gender": "male",
    "Paid": true
  },
  {
    "ID": 538,
    "Firstname": "Paul",
    "Lastname": "Becker",
    "Name": "Paul Becker",
    "Birthyear": 2001,
    "Club": "JC Hannover",
    "Association": "NJV",
    "Weight": 0.0,
    "Valid": false,
    "Gender": "male",
    "Paid": true
  },
  {
    "ID": 541,
    "Firstname": "Max",
    "Lastname": "Bauer",
    "Name": "Max Bauer",
    "Birthyear": 2017,
    "Club": "PSV Frankfurt",
    "Association": "HJV",
    "Weight": 0.0,
    "Valid": false,
    "Gender": "male",
    "Paid": true
  },
  {
    "ID": 542,
    "Firstname": "Noah",
    "Lastname": "Wagner",
    "Name": "Noah Wagner",
    "Birthyear": 2005,
    "Club": "Budosport Stuttgart",
    "Association": "WJV",
    "Weight": 0.0,
    "Valid": false,
    "Gender": "male",
    "Paid": true
  },
  {
    "ID": 543,
    "Firstname": "Elias",
    "Lastname": "Becker",
    "Name": "Elias Becker",
    "Birthyear": 2016,
    "Club": "PSV Frankfurt",
    "Association": "HJV",
    "Weight": 0.0,
    "Valid": false,
    "Gender": "male",
    "Paid": true
  },
  {
    "ID": 544,
    "Firstname": "Tim",
    "Lastname": "Weber",
    "Name": "Tim Weber",
    "Birthyear": 1998,
    "Club": "MTV Karlsruhe",
    "Association": "BJV",
    "Weight": 0.0,
    "Valid": false,
    "Gender": "male",
    "Paid": false
  },
  {
    "ID": 545,
    "Firstname": "Elias",
    "Lastname": "Koch",
    "Name": "Elias Koch",
    "Birthyear": 2009,
    "Club": "JC Leipzig",
    "Association": "JV Sachsen",
    "Weight": 0.0,
    "Valid": false,
    "Gender": "male",
    "Paid": false
  },
  {
    "ID": 550,
    "Firstname": "Finn",
    "Lastname": "Weber",
    "Name": "Finn Weber",
    "Birthyear": 2014,
    "Club": "Budosport Stuttgart",
    "Association": "WJV",
    "Weight": 0.0,
    "Valid": false,
    "Gender": "male",
    "Paid": false
  },
  {
    "ID": 558,
    "Firstname": "Jonas",
    "Lastname": "Wagner",
    "Name": "Jonas Wagner",
    "Birthyear": 1996,
    "Club": "JC Hamburg Nord",
    "Association": "HJV",
    "Weight": 0.0,
    "Valid": false,
    "Gender": "male",
    "Paid": true
  },
  {
    "ID": 559,
    "Firstname": "Max",
    "Lastname": "Schmidt",
    "Name": "Max Schmidt",
    "Birthyear": 2011,
    "Club": "JC Hamburg Nord",
    "Association": "HJV",
    "Weight": 0.0,
    "Valid": false,
    "Gender": "male",
    "Paid": false
  },
  {
    "ID": 560,
    "Firstname": "Elias",
    "Lastname": "Fischer",
    "Name": "Elias Fischer",
    "Birthyear": 2016,
    "Club": "JC Hamburg Nord",
    "Association": "HJV",
    "Weight": 0.0,
    "Valid": false,
    "Gender": "male",
    "Paid": true
  },
  {
    "ID": 561,
    "Firstname": "Tim",
    "Lastname": "Schneider",
    "Name": "Tim Schneider",
    "Birthyear": 2006,
    "Club": "JC Berlin Süd",
    "Association": "JV Berlin",
    "Weight": 0.0,
    "Valid": false,
    "Gender": "male",
    "Paid": false
  },
  {
    "ID": 562,
    "Firstname": "Moritz",
    "Lastname": "Müller",
    "Name": "Moritz Müller",
    "Birthyear": 2012,
    "Club": "JC München",
    "Association": "BJV",
    "Weight": 0.0,
    "Valid": false,
    "Gender": "male",
    "Paid": true
  },
  {
    "ID": 563,
    "Firstname": "Lukas",
    "Lastname": "Wagner",
    "Name": "Lukas Wagner",
    "Birthyear": 2017,
    "Club": "TSV Köln",
    "Association": "NWJV",
    "Weight": 0.0,
    "Valid": false,
    "Gender": "male",
    "Paid": true
  },
  {
    "ID": 566,
    "Firstname": "Tom",
    "Lastname": "Meyer",
    "Name": "Tom Meyer",
    "Birthyear": 2011,
    "Club": "PSV Frankfurt",
    "Association": "HJV",
    "Weight": 0.0,
    "Valid": false,
    "Gender": "male",
    "Paid": true
  },
  {
    "ID": 567,
    "Firstname": "Noah",
    "Lastname": "Müller",
    "Name": "Noah Müller",
    "Birthyear": 1996,
    "Club": "JC Leipzig",
    "Association": "JV Sachsen",
    "Weight": 0.0,
    "Valid": false,
    "Gender": "male",
    "Paid": false
  },
  {
    "ID": 570,
    "Firstname": "Lukas",
    "Lastname": "Bauer",
    "Name": "Lukas Bauer",
    "Birthyear": 1996,
    "Club": "Budosport Stuttgart",
    "Association": "WJV",
    "Weight": 0.0,
    "Valid": false,
    "Gender": "male",
    "Paid": false
  },
  {
    "ID": 571,
    "Firstname": "Tim",
    "Lastname": "Weber",
    "Name": "Tim Weber",
    "Birthyear": 2016,
    "Club": "JC München",
    "Association": "BJV",
    "Weight": 0.0,
    "Valid": false,
    "Gender": "male",
    "Paid": true
  },
  {
    "ID": 574,
    "Firstname": "Paul",
    "Lastname": "Schäfer",
    "Name": "Paul Schäfer",
    "Birthyear": 2004,
    "Club": "Budosport Stuttgart",
    "Association": "WJV",
    "Weight": 0.0,
    "Valid": false,
    "Gender": "male",
    "Paid": false
  },
  {
    "ID": 575,
    "Firstname": "Ben",
    "Lastname": "Wagner",
    "Name": "Ben Wagner",
    "Birthyear": 2009,
    "Club": "JC Berlin Süd",
    "Association": "JV Berlin",
    "Weight": 0.0,
    "Valid": false,
    "Gender": "male",
    "Paid": true
  },
  {
    "ID": 576,
    "Firstname": "Moritz",
    "Lastname": "Müller",
    "Name": "Moritz Müller",
    "Birthyear": 2012,
    "Club": "JC Berlin Süd",
    "Association": "JV Berlin",
    "Weight": 0.0,
    "Valid": false,
    "Gender": "male",
    "Paid": false
  },
  {
    "ID": 577,
    "Firstname": "Finn",
    "Lastname": "Wagner",
    "Name": "Finn Wagner",
    "Birthyear": 2010,
    "Club": "JC Leipzig",
    "Association": "JV Sachsen",
    "Weight": 0.0,
    "Valid": false,
    "Gender": "male",
    "Paid": true
  },
  {
    "ID": 578,
    "Firstname": "Noah",
    "Lastname": "Schneider",
    "Name": "Noah Schneider",
    "Birthyear": 2011,
    "Club": "PSV Frankfurt",
    "Association": "HJV",
    "Weight": 0.0,
    "Valid": false,
    "Gender": "male",
    "Paid": true
  },
  {
    "ID": 580,
    "Firstname": "Ben",
    "Lastname": "Fischer",
    "Name": "Ben Fischer",
    "Birthyear": 2015,
    "Club": "JC Hamburg Nord",
    "Association": "HJV",
    "Weight": 0.0,
    "Valid": false,
    "Gender": "male",
    "Paid": true
  },
  {
    "ID": 581,
    "Firstname": "Finn",
    "Lastname": "Müller",
    "Name": "Finn Müller",
    "Birthyear": 2006,
    "Club": "MTV Karlsruhe",
    "Association": "BJV",
    "Weight": 0.0,
    "Valid": false,
    "Gender": "male",
    "Paid": false
  },
  {
    "ID": 584,
    "Firstname": "Jonas",
    "Lastname": "Schäfer",
    "Name": "Jonas Schäfer",
    "Birthyear": 2015,
    "Club": "Budosport Stuttgart",
    "Association": "WJV",
    "Weight": 0.0,
    "Valid": false,
    "Gender": "male",
    "Paid": false
  },
  {
    "ID": 585,
    "Firstname": "Elias",
    "Lastname": "Fischer",
    "Name": "Elias Fischer",
    "Birthyear": 2015,
    "Club": "JC Hannover",
    "Association": "NJV",
    "Weight": 0.0,
    "Valid": false,
    "Gender": "male",
    "Paid": true
  },
  {
    "ID": 586,
    "Firstname": "Leon",
    "Lastname": "Meyer",
    "Name": "Leon Meyer",
    "Birthyear": 2011,
    "Club": "SV Potsdam",
    "Association": "JV Berlin",
    "Weight": 0.0,
    "Valid": false,
    "Gender": "male",
    "Paid": false
  },
  {
    "ID": 587,
    "Firstname": "Tomm",
    "Lastname": "Becker",
    "Name": "Tomm Becker",
    "Birthyear": 2014,
    "Club": "Budosport Stuttgart",
    "Association": "WJV",
    "Weight": 0.0,
    "Valid": false,
    "Gender": "male",
    "Paid": true
  },
  {
    "ID": 589,
    "Firstname": "Moritz",
    "Lastname": "Hoffmann",
    "Name": "Moritz Hoffmann",
    "Birthyear": 2008,
    "Club": "Budosport Stuttgart",
    "Association": "WJV",
    "Weight": 0.0,
    "Valid": false,
    "Gender": "male",
    "Paid": false
  },
  {
    "ID": 590,
    "Firstname": "Finn",
    "Lastname": "Schäfer",
    "Name": "Finn Schäfer",
    "Birthyear": 2011,
    "Club": "MTV Karlsruhe",
    "Association": "BJV",
    "Weight": 0.0,
    "Valid": false,
    "Gender": "male",
    "Paid": true
  },
  {
    "ID": 592,
    "Firstname": "Lukas",
    "Lastname": "Wagner",
    "Name": "Lukas Wagner",
    "Birthyear": 2017,
    "Club": "TSV Köln",
    "Association": "NWJV",
    "Weight": 0.0,
    "Valid": false,
    "Gender": "male",
    "Paid": true
  },
  {
    "ID": 599,
    "Firstname": "Elias",
    "Lastname": "Wagner",
    "Name": "Elias Wagner",
    "Birthyear": 2011,
    "Club": "SV Potsdam",
    "Association": "JV Berlin",
    "Weight": 0.0,
    "Valid": false,
    "Gender": "male",
    "Paid": false
  },
  {
    "ID": 605,
    "Firstname": "Noah",
    "Lastname": "Becker",
    "Name": "Noah Becker",
    "Birthyear": 2016,
    "Club": "JC Leipzig",
    "Association": "JV Sachsen",
    "Weight": 0.0,
    "Valid": false,
    "Gender": "male",
    "Paid": true
  },
  {
    "ID": 607,
    "Firstname": "Jonas",
    "Lastname": "Wagner",
    "Name": "Jonas Wagner",
    "Birthyear": 2009,
    "Club": "TSV Köln",
    "Association": "NWJV",
    "Weight": 0.0,
    "Valid": false,
    "Gender": "male",
    "Paid": true
  },
  {
    "ID": 608,
    "Firstname": "Lukas",
    "Lastname": "Weber",
    "Name": "Lukas Weber",
    "Birthyear": 2012,
    "Club": "JC München",
    "Association": "BJV",
    "Weight": 0.0,
    "Valid": false,
    "Gender": "male",
    "Paid": true
  },
  {
    "ID": 609,
    "Firstname": "Lukas",
    "Lastname": "Wagner",
    "Name": "Lukas Wagner",
    "Birthyear": 2012,
    "Club": "JC Berlin Süd",
    "Association": "JV Berlin",
    "Weight": 0.0,
    "Valid": false,
    "Gender": "male",
    "Paid": true
  },
  {
    "ID": 610,
    "Firstname": "Moritz",
    "Lastname": "Bauer",
    "Name": "Moritz Bauer",
    "Birthyear": 2016,
    "Club": "JC Leipzig",
    "Association": "JV Sachsen",
    "Weight": 0.0,
    "Valid": false,
    "Gender": "male",
    "Paid": true
  },
  {
    "ID": 611,
    "Firstname": "Paul",
    "Lastname": "Schäfer",
    "Name": "Paul Schäfer",
    "Birthyear": 2012,
    "Club": "JC Hamburg Nord",
    "Association": "HJV",
    "Weight": 0.0,
    "Valid": false,
    "Gender": "male",
    "Paid": true
  },
  {
    "ID": 612,
    "Firstname": "Leon",
    "Lastname": "Hoffmann",
    "Name": "Leon Hoffmann",
    "Birthyear": 2014,
    "Club": "JC Hamburg Nord",
    "Association": "HJV",
    "Weight": 0.0,
    "Valid": false,
    "Gender": "male",
    "Paid": false
  },
  {
    "ID": 613,
    "Firstname": "Tim",
    "Lastname": "Müller",
    "Name": "Tim Müller",
    "Birthyear": 2019,
    "Club": "JC Leipzig",
    "Association": "JV Sachsen",
    "Weight": 0.0,
    "Valid": false,
    "Gender": "male",
    "Paid": false
  },
  {
    "ID": 616,
    "Firstname": "Finn",
    "Lastname": "Fischer",
    "Name": "Finn Fischer",
    "Birthyear": 2013,
    "Club": "Budosport Stuttgart",
    "Association": "WJV",
    "Weight": 0.0,
    "Valid": false,
    "Gender": "male",
    "Paid": true
  },
  {
    "ID": 617,
    "Firstname": "Lukas",
    "Lastname": "Hoffmann",
    "Name": "Lukas Hoffmann",
    "Birthyear": 2008,
    "Club": "JC Berlin Süd",
    "Association": "JV Berlin",
    "Weight": 0.0,
    "Valid": false,
    "Gender": "male",
    "Paid": false
  },
  {
    "ID": 619,
    "Firstname": "Moritz",
    "Lastname": "Bauer",
    "Name": "Moritz Bauer",
    "Birthyear": 2011,
    "Club": "JC Hannover",
    "Association": "NJV",
    "Weight": 0.0,
    "Valid": false,
    "Gender": "male",
    "Paid": false
  },
  {
    "ID": 620,
    "Firstname": "Elias",
    "Lastname": "Weber",
    "Name": "Elias Weber",
    "Birthyear": 2018,
    "Club": "JC München",
    "Association": "BJV",
    "Weight": 0.0,
    "Valid": false,
    "Gender": "male",
    "Paid": true
  },
  {
    "ID": 625,
    "Firstname": "Max",
    "Lastname": "Fischer",
    "Name": "Max Fischer",
    "Birthyear": 2010,
    "Club": "Budosport Stuttgart",
    "Association": "WJV",
    "Weight": 0.0,
    "Valid": false,
    "Gender": "male",
    "Paid": true
  },
  {
    "ID": 627,
    "Firstname": "Paul",
    "Lastname": "Hoffmann",
    "Name": "Paul Hoffmann",
    "Birthyear": 2016,
    "Club": "JC Hannover",
    "Association": "NJV",
    "Weight": 0.0,
    "Valid": false,
    "Gender": "male",
    "Paid": true
  },
  {
    "ID": 628,
    "Firstname": "Max",
    "Lastname": "Bauer",
    "Name": "Max Bauer",
    "Birthyear": 1999,
    "Club": "PSV Frankfurt",
    "Association": "HJV",
    "Weight": 0.0,
    "Valid": false,
    "Gender": "male",
    "Paid": true
  },
  {
    "ID": 631,
    "Firstname": "Lukas",
    "Lastname": "Becker",
    "Name": "Lukas Becker",
    "Birthyear": 2011,
    "Club": "TSV Köln",
    "Association": "NWJV",
    "Weight": 0.0,
    "Valid": false,
    "Gender": "male",
    "Paid": true
  },
  {
    "ID": 633,
    "Firstname": "Jonas",
    "Lastname": "Koch",
    "Name": "Jonas Koch",
    "Birthyear": 2013,
    "Club": "JC Hannover",
    "Association": "NJV",
    "Weight": 0.0,
    "Valid": false,
    "Gender": "male",
    "Paid": false
  },
  {
    "ID": 634,
    "Firstname": "Max",
    "Lastname": "Wagner",
    "Name": "Max Wagner",
    "Birthyear": 2019,
    "Club": "PSV Frankfurt",
    "Association": "HJV",
    "Weight": 0.0,
    "Valid": false,
    "Gender": "male",
    "Paid": true
  },
  {
    "ID": 635,
    "Firstname": "Leon",
    "Lastname": "Schmidt",
    "Name": "Leon Schmidt",
    "Birthyear": 2009,
    "Club": "TSV Köln",
    "Association": "NWJV",
    "Weight": 0.0,
    "Valid": false,
    "Gender": "male",
    "Paid": false
  },
  {
    "ID": 636,
    "Firstname": "Leon",
    "Lastname": "Schmidt",
    "Name": "Leon Schmidt",
    "Birthyear": 2013,
    "Club": "JC Hamburg Nord",
    "Association": "HJV",
    "Weight": 0.0,
    "Valid": false,
    "Gender": "male",
    "Paid": false
  },
  {
    "ID": 638,
    "Firstname": "Leon",
    "Lastname": "Wagner",
    "Name": "Leon Wagner",
    "Birthyear": 2010,
    "Club": "JC Hannover",
    "Association": "NJV",
    "Weight": 0.0,
    "Valid": false,
    "Gender": "male",
    "Paid": true
  },
  {
    "ID": 643,
    "Firstname": "Jonas",
    "Lastname": "Müller",
    "Name": "Jonas Müller",
    "Birthyear": 2018,
    "Club": "JC München",
    "Association": "BJV",
    "Weight": 0.0,
    "Valid": false,
    "Gender": "male",
    "Paid": false
  },
  {
    "ID": 647,
    "Firstname": "Leon",
    "Lastname": "Weber",
    "Name": "Leon Weber",
    "Birthyear": 2009,
    "Club": "JC Leipzig",
    "Association": "JV Sachsen",
    "Weight": 0.0,
    "Valid": false,
    "Gender": "male",
    "Paid": false
  },
  {
    "ID": 649,
    "Firstname": "Tom",
    "Lastname": "Weber",
    "Name": "Tom Weber",
    "Birthyear": 2017,
    "Club": "MTV Karlsruhe",
    "Association": "BJV",
    "Weight": 0.0,
    "Valid": false,
    "Gender": "male",
    "Paid": false
  },
  {
    "ID": 650,
    "Firstname": "Jonas",
    "Lastname": "Schäfer",
    "Name": "Jonas Schäfer",
    "Birthyear": 2009,
    "Club": "JC Hamburg Nord",
    "Association": "HJV",
    "Weight": 0.0,
    "Valid": false,
    "Gender": "male",
    "Paid": true
  },
  {
    "ID": 651,
    "Firstname": "Max",
    "Lastname": "Schmidt",
    "Name": "Max Schmidt",
    "Birthyear": 2010,
    "Club": "Budosport Stuttgart",
    "Association": "WJV",
    "Weight": 0.0,
    "Valid": false,
    "Gender": "male",
    "Paid": false
  },
  {
    "ID": 653,
    "Firstname": "Ben",
    "Lastname": "Schmidt",
    "Name": "Ben Schmidt",
    "Birthyear": 2008,
    "Club": "JC Berlin Süd",
    "Association": "JV Berlin",
    "Weight": 0.0,
    "Valid": false,
    "Gender": "male",
    "Paid": false
  },
  {
    "ID": 654,
    "Firstname": "Elias",
    "Lastname": "Schmidt",
    "Name": "Elias Schmidt",
    "Birthyear": 2018,
    "Club": "JC Leipzig",
    "Association": "JV Sachsen",
    "Weight": 0.0,
    "Valid": false,
    "Gender": "male",
    "Paid": false
  },
  {
    "ID": 655,
    "Firstname": "Max",
    "Lastname": "Weber",
    "Name": "Max Weber",
    "Birthyear": 2012,
    "Club": "JC Leipzig",
    "Association": "JV Sachsen",
    "Weight": 0.0,
    "Valid": false,
    "Gender": "male",
    "Paid": false
  },
  {
    "ID": 658,
    "Firstname": "Lukas",
    "Lastname": "Meyer",
    "Name": "Lukas Meyer",
    "Birthyear": 2008,
    "Club": "JC Berlin Süd",
    "Association": "JV Berlin",
    "Weight": 0.0,
    "Valid": false,
    "Gender": "male",
    "Paid": false
  },
  {
    "ID": 659,
    "Firstname": "Elias",
    "Lastname": "Meyer",
    "Name": "Elias Meyer",
    "Birthyear": 2001,
    "Club": "JC Berlin Süd",
    "Association": "JV Berlin",
    "Weight": 0.0,
    "Valid": false,
    "Gender": "male",
    "Paid": false
  },
  {
    "ID": 664,
    "Firstname": "Ben",
    "Lastname": "Schmidt",
    "Name": "Ben Schmidt",
    "Birthyear": 2012,
    "Club": "JC Berlin Süd",
    "Association": "JV Berlin",
    "Weight": 0.0,
    "Valid": false,
    "Gender": "male",
    "Paid": true
  },
  {
    "ID": 665,
    "Firstname": "Moritz",
    "Lastname": "Hoffmann",
    "Name": "Moritz Hoffmann",
    "Birthyear": 2011,
    "Club": "JC Berlin Süd",
    "Association": "JV Berlin",
    "Weight": 0.0,
    "Valid": false,
    "Gender": "male",
    "Paid": false
  },
  {
    "ID": 668,
    "Firstname": "Lukas",
    "Lastname": "Schäfer",
    "Name": "Lukas Schäfer",
    "Birthyear": 2011,
    "Club": "SV Potsdam",
    "Association": "JV Berlin",
    "Weight": 0.0,
    "Valid": false,
    "Gender": "male",
    "Paid": true
  },
  {
    "ID": 670,
    "Firstname": "Noah",
    "Lastname": "Schäfer",
    "Name": "Noah Schäfer",
    "Birthyear": 2014,
    "Club": "JC Hannover",
    "Association": "NJV",
    "Weight": 0.0,
    "Valid": false,
    "Gender": "male",
    "Paid": true
  },
  {
    "ID": 671,
    "Firstname": "Tom",
    "Lastname": "Weber",
    "Name": "Tom Weber",
    "Birthyear": 2012,
    "Club": "JC Hannover",
    "Association": "NJV",
    "Weight": 0.0,
    "Valid": false,
    "Gender": "male",
    "Paid": false
  },
  {
    "ID": 673,
    "Firstname": "Noah",
    "Lastname": "Hoffmann",
    "Name": "Noah Hoffmann",
    "Birthyear": 2010,
    "Club": "Budosport Stuttgart",
    "Association": "WJV",
    "Weight": 0.0,
    "Valid": false,
    "Gender": "male",
    "Paid": true
  },
  {
    "ID": 674,
    "Firstname": "Jonas",
    "Lastname": "Schmidt",
    "Name": "Jonas Schmidt",
    "Birthyear": 2015,
    "Club": "Budosport Stuttgart",
    "Association": "WJV",
    "Weight": 0.0,
    "Valid": false,
    "Gender": "male",
    "Paid": false
  },
  {
    "ID": 675,
    "Firstname": "Max",
    "Lastname": "Müller",
    "Name": "Max Müller",
    "Birthyear": 2015,
    "Club": "PSV Frankfurt",
    "Association": "HJV",
    "Weight": 0.0,
    "Valid": false,
    "Gender": "male",
    "Paid": false
  },
  {
    "ID": 679,
    "Firstname": "Ben",
    "Lastname": "Koch",
    "Name": "Ben Koch",
    "Birthyear": 2012,
    "Club": "JC Leipzig",
    "Association": "JV Sachsen",
    "Weight": 0.0,
    "Valid": false,
    "Gender": "male",
    "Paid": true
  },
  {
    "ID": 681,
    "Firstname": "Finn",
    "Lastname": "Bauer",
    "Name": "Finn Bauer",
    "Birthyear": 2011,
    "Club": "MTV Karlsruhe",
    "Association": "BJV",
    "Weight": 0.0,
    "Valid": false,
    "Gender": "male",
    "Paid": false
  },
  {
    "ID": 682,
    "Firstname": "Finn",
    "Lastname": "Müller",
    "Name": "Finn Müller",
    "Birthyear": 2018,
    "Club": "JC Hannover",
    "Association": "NJV",
    "Weight": 0.0,
    "Valid": false,
    "Gender": "male",
    "Paid": true
  },
  {
    "ID": 684,
    "Firstname": "Leon",
    "Lastname": "Koch",
    "Name": "Leon Koch",
    "Birthyear": 2015,
    "Club": "JC Leipzig",
    "Association": "JV Sachsen",
    "Weight": 0.0,
    "Valid": false,
    "Gender": "male",
    "Paid": true
  },
  {
    "ID": 685,
    "Firstname": "Paul",
    "Lastname": "Koch",
    "Name": "Paul Koch",
    "Birthyear": 2015,
    "Club": "PSV Frankfurt",
    "Association": "HJV",
    "Weight": 0.0,
    "Valid": false,
    "Gender": "male",
    "Paid": false
  },
  {
    "ID": 687,
    "Firstname": "Lukas",
    "Lastname": "Weber",
    "Name": "Lukas Weber",
    "Birthyear": 2015,
    "Club": "PSV Frankfurt",
    "Association": "HJV",
    "Weight": 0.0,
    "Valid": false,
    "Gender": "male",
    "Paid": false
  },
  {
    "ID": 688,
    "Firstname": "Ben",
    "Lastname": "Weber",
    "Name": "Ben Weber",
    "Birthyear": 2017,
    "Club": "SV Potsdam",
    "Association": "JV Berlin",
    "Weight": 0.0,
    "Valid": false,
    "Gender": "male",
    "Paid": true
  },
  {
    "ID": 690,
    "Firstname": "Finn",
    "Lastname": "Bauer",
    "Name": "Finn Bauer",
    "Birthyear": 2010,
    "Club": "Budosport Stuttgart",
    "Association": "WJV",
    "Weight": 0.0,
    "Valid": false,
    "Gender": "male",
    "Paid": false
  },
  {
    "ID": 692,
    "Firstname": "Tom",
    "Lastname": "Becker",
    "Name": "Tom Becker",
    "Birthyear": 2011,
    "Club": "SV Potsdam",
    "Association": "JV Berlin",
    "Weight": 0.0,
    "Valid": false,
    "Gender": "male",
    "Paid": false
  },
  {
    "ID": 693,
    "Firstname": "Elias",
    "Lastname": "Meyer",
    "Name": "Elias Meyer",
    "Birthyear": 2014,
    "Club": "JC Leipzig",
    "Association": "JV Sachsen",
    "Weight": 0.0,
    "Valid": false,
    "Gender": "male",
    "Paid": false
  },
  {
    "ID": 694,
    "Firstname": "Elias",
    "Lastname": "Meyer",
    "Name": "Elias Meyer",
    "Birthyear": 2010,
    "Club": "TSV Köln",
    "Association": "NWJV",
    "Weight": 0.0,
    "Valid": false,
    "Gender": "male",
    "Paid": false
  },
  {
    "ID": 695,
    "Firstname": "Tim",
    "Lastname": "Koch",
    "Name": "Tim Koch",
    "Birthyear": 2015,
    "Club": "PSV Frankfurt",
    "Association": "HJV",
    "Weight": 0.0,
    "Valid": false,
    "Gender": "male",
    "Paid": false
  },
  {
    "ID": 700,
    "Firstname": "Leon",
    "Lastname": "Schmidt",
    "Name": "Leon Schmidt",
    "Birthyear": 2002,
    "Club": "JC Leipzig",
    "Association": "JV Sachsen",
    "Weight": 0.0,
    "Valid": false,
    "Gender": "male",
    "Paid": false
  },
  {
    "ID": 701,
    "Firstname": "Jonas",
    "Lastname": "Schäfer",
    "Name": "Jonas Schäfer",
    "Birthyear": 2009,
    "Club": "JC Hamburg Nord",
    "Association": "HJV",
    "Weight": 0.0,
    "Valid": false,
    "Gender": "male",
    "Paid": false
  },
  {
    "ID": 702,
    "Firstname": "Max",
    "Lastname": "Schmidt",
    "Name": "Max Schmidt",
    "Birthyear": 2010,
    "Club": "Budosport Stuttgart",
    "Association": "WJV",
    "Weight": 0.0,
    "Valid": false,
    "Gender": "male",
    "Paid": true
  },
  {
    "ID": 704,
    "Firstname": "Ben",
    "Lastname": "Schmidt",
    "Name": "Ben Schmidt",
    "Birthyear": 2008,
    "Club": "JC Berlin Süd",
    "Association": "JV Berlin",
    "Weight": 0.0,
    "Valid": false,
    "Gender": "male",
    "Paid": false
  },
  {
    "ID": 705,
    "Firstname": "Elias",
    "Lastname": "Schmidt",
    "Name": "Elias Schmidt",
    "Birthyear": 2018,
    "Club": "JC Leipzig",
    "Association": "JV Sachsen",
    "Weight": 0.0,
    "Valid": false,
    "Gender": "male",
    "Paid": false
  },
  {
    "ID": 706,
    "Firstname": "Max",
    "Lastname": "Weber",
    "Name": "Max Weber",
    "Birthyear": 2012,
    "Club": "JC Leipzig",
    "Association": "JV Sachsen",
    "Weight": 0.0,
    "Valid": false,
    "Gender": "male",
    "Paid": true
  },
  {
    "ID": 709,
    "Firstname": "Lukas",
    "Lastname": "Meyer",
    "Name": "Lukas Meyer",
    "Birthyear": 2008,
    "Club": "JC Berlin Süd",
    "Association": "JV Berlin",
    "Weight": 0.0,
    "Valid": false,
    "Gender": "male",
    "Paid": true
  },
  {
    "ID": 710,
    "Firstname": "Elias",
    "Lastname": "Meyer",
    "Name": "Elias Meyer",
    "Birthyear": 2001,
    "Club": "JC Berlin Süd",
    "Association": "JV Berlin",
    "Weight": 0.0,
    "Valid": false,
    "Gender": "male",
    "Paid": true
  },
  {
    "ID": 715,
    "Firstname": "Ben",
    "Lastname": "Schmidt",
    "Name": "Ben Schmidt",
    "Birthyear": 2012,
    "Club": "JC Berlin Süd",
    "Association": "JV Berlin",
    "Weight": 0.0,
    "Valid": false,
    "Gender": "male",
    "Paid": false
  },
  {
    "ID": 716,
    "Firstname": "Moritz",
    "Lastname": "Hoffmann",
    "Name": "Moritz Hoffmann",
    "Birthyear": 2011,
    "Club": "JC Berlin Süd",
    "Association": "JV Berlin",
    "Weight": 0.0,
    "Valid": false,
    "Gender": "male",
    "Paid": false
  },
  {
    "ID": 719,
    "Firstname": "Lukas",
    "Lastname": "Schäfer",
    "Name": "Lukas Schäfer",
    "Birthyear": 2011,
    "Club": "SV Potsdam",
    "Association": "JV Berlin",
    "Weight": 0.0,
    "Valid": false,
    "Gender": "male",
    "Paid": false
  },
  {
    "ID": 721,
    "Firstname": "Noah",
    "Lastname": "Schäfer",
    "Name": "Noah Schäfer",
    "Birthyear": 2014,
    "Club": "JC Hannover",
    "Association": "NJV",
    "Weight": 0.0,
    "Valid": false,
    "Gender": "male",
    "Paid": false
  },
  {
    "ID": 722,
    "Firstname": "Tom",
    "Lastname": "Weber",
    "Name": "Tom Weber",
    "Birthyear": 2012,
    "Club": "JC Hannover",
    "Association": "NJV",
    "Weight": 0.0,
    "Valid": false,
    "Gender": "male",
    "Paid": false
  },
  {
    "ID": 724,
    "Firstname": "Noah",
    "Lastname": "Hoffmann",
    "Name": "Noah Hoffmann",
    "Birthyear": 2010,
    "Club": "Budosport Stuttgart",
    "Association": "WJV",
    "Weight": 0.0,
    "Valid": false,
    "Gender": "male",
    "Paid": true
  },
  {
    "ID": 725,
    "Firstname": "Jonas",
    "Lastname": "Schmidt",
    "Name": "Jonas Schmidt",
    "Birthyear": 2015,
    "Club": "Budosport Stuttgart",
    "Association": "WJV",
    "Weight": 0.0,
    "Valid": false,
    "Gender": "male",
    "Paid": true
  },
  {
    "ID": 726,
    "Firstname": "Max",
    "Lastname": "Müller",
    "Name": "Max Müller",
    "Birthyear": 2015,
    "Club": "PSV Frankfurt",
    "Association": "HJV",
    "Weight": 0.0,
    "Valid": false,
    "Gender": "male",
    "Paid": false
  },
  {
    "ID": 730,
    "Firstname": "Ben",
    "Lastname": "Koch",
    "Name": "Ben Koch",
    "Birthyear": 2012,
    "Club": "JC Leipzig",
    "Association": "JV Sachsen",
    "Weight": 0.0,
    "Valid": false,
    "Gender": "male",
    "Paid": true
  },
  {
    "ID": 732,
    "Firstname": "Finn",
    "Lastname": "Bauer",
    "Name": "Finn Bauer",
    "Birthyear": 2011,
    "Club": "MTV Karlsruhe",
    "Association": "BJV",
    "Weight": 0.0,
    "Valid": false,
    "Gender": "male",
    "Paid": true
  },
  {
    "ID": 733,
    "Firstname": "Finn",
    "Lastname": "Müller",
    "Name": "Finn Müller",
    "Birthyear": 2018,
    "Club": "JC Hannover",
    "Association": "NJV",
    "Weight": 0.0,
    "Valid": false,
    "Gender": "male",
    "Paid": true
  },
  {
    "ID": 735,
    "Firstname": "Leon",
    "Lastname": "Koch",
    "Name": "Leon Koch",
    "Birthyear": 2015,
    "Club": "JC Leipzig",
    "Association": "JV Sachsen",
    "Weight": 0.0,
    "Valid": false,
    "Gender": "male",
    "Paid": true
  },
  {
    "ID": 736,
    "Firstname": "Paul",
    "Lastname": "Koch",
    "Name": "Paul Koch",
    "Birthyear": 2015,
    "Club": "PSV Frankfurt",
    "Association": "HJV",
    "Weight": 0.0,
    "Valid": false,
    "Gender": "male",
    "Paid": false
  },
  {
    "ID": 738,
    "Firstname": "Lukas",
    "Lastname": "Weber",
    "Name": "Lukas Weber",
    "Birthyear": 2015,
    "Club": "PSV Frankfurt",
    "Association": "HJV",
    "Weight": 0.0,
    "Valid": false,
    "Gender": "male",
    "Paid": false
  },
  {
    "ID": 739,
    "Firstname": "Esel",
    "Lastname": "VonShrek",
    "Name": "Esel VonShrek",
    "Birthyear": 1453,
    "Club": "SV Potsdam",
    "Association": "JV Berlin",
    "Weight": 0.0,
    "Valid": false,
    "Gender": "male",
    "Paid": false
  },
  {
    "ID": 741,
    "Firstname": "Larry",
    "Lastname": "Spitzkopf",
    "Name": "Larry Spitzkopf",
    "Birthyear": 1969,
    "Club": "Budosport Stuttgart",
    "Association": "WJV",
    "Weight": 0.0,
    "Valid": false,
    "Gender": "male",
    "Paid": true
  },
  {
    "ID": 742,
    "Firstname": "Neckless",
    "Lastname": "Gambler",
    "Name": "Neckless Gambler",
    "Birthyear": 1861,
    "Club": "PSV Frankfurt",
    "Association": "HJV",
    "Weight": 0.0,
    "Valid": false,
    "Gender": "male",
    "Paid": false
  },
  {
    "ID": 743,
    "Firstname": "Baby",
    "Lastname": "Mastodon",
    "Name": "Baby Mastodon",
    "Birthyear": 2020,
    "Club": "SV Potsdam",
    "Association": "JV Berlin",
    "Weight": 0.0,
    "Valid": false,
    "Gender": "male",
    "Paid": true
  },
  {
    "ID": 744,
    "Firstname": "Heftiger",
    "Lastname": "Hans",
    "Name": "Heftiger Hans",
    "Birthyear": 2009,
    "Club": "JC Leipzig",
    "Association": "JV Sachsen",
    "Weight": 0.0,
    "Valid": false,
    "Gender": "male",
    "Paid": false
  },
  {
    "ID": 745,
    "Firstname": "Felxi",
    "Lastname": "Seilheimer",
    "Name": "Felxi Seilheimer",
    "Birthyear": 2003,
    "Club": "TSV Köln",
    "Association": "NWJV",
    "Weight": 0.0,
    "Valid": false,
    "Gender": "male",
    "Paid": true
  },
  {
    "ID": 746,
    "Firstname": "Ssiawosch",
    "Lastname": "Sadat",
    "Name": "Ssiawosch Sadat",
    "Birthyear": 2015,
    "Club": "PSV Frankfurt",
    "Association": "HJV",
    "Weight": 0.0,
    "Valid": false,
    "Gender": "male",
    "Paid": true
  },
  {
    "ID": 748,
    "Firstname": "Forelle",
    "Lastname": "Fisch",
    "Name": "Forelle Fisch",
    "Birthyear": 2025,
    "Club": "JC Hannover",
    "Association": "NJV",
    "Weight": 0.0,
    "Valid": false,
    "Gender": "male",
    "Paid": true
  },
  {
    "ID": 750,
    "Firstname": "Tobias",
    "Lastname": "Hoffmann",
    "Name": "Tobias Hoffmann",
    "Birthyear": 1900,
    "Club": "JC München",
    "Association": "BJV",
    "Weight": 0.0,
    "Valid": false,
    "Gender": "male",
    "Paid": true
  },
  {
    "ID": 751,
    "Firstname": "Hadlik",
    "Lastname": "Merlin+",
    "Name": "Hadlik Merlin+",
    "Birthyear": 1906,
    "Club": "JC Leipzig",
    "Association": "JV Sachsen",
    "Weight": 0.0,
    "Valid": false,
    "Gender": "m",
    "Paid": true
  },
  {
    "ID": 752,
    "Firstname": "Wolfgang",
    "Lastname": "Jeblick",
    "Name": "Wolfgang Jeblick",
    "Birthyear": 1997,
    "Club": null,
    "Weight": 0.0,
    "Valid": false,
    "Gender": "m",
    "Paid": false
  },
  {
    "ID": 753,
    "Firstname": "Merlin",
    "Lastname": "Hladikiii",
    "Name": "Merlin Hladikiii",
    "Birthyear": 1998,
    "Club": "Deidesheim",
    "Weight": 0.0,
    "Valid": false,
    "Gender": "m",
    "Paid": false
  }
]